Workbook

Sheet Спецификация
A1: № п/п | B1: Наименование и техническая характеристика | C1: Тип, марка, обозначение документа, опросного листа | D1: Код оборудования, изделия, материала | E1: Поставщик | F1: Ед. изм. | G1: Кол-во | H1: Цена, руб. с НДС | I1: Сумма, руб. с НДС | J1: Масса единицы, кг | K1: Примечание
A2: ЛОГИСТИКА — ПЕРЕВОЗКА ГРУЗОВ (наша, точка А → точка Б; из ВОРов)
A3: ВОР 20 | B3: Перевозка грузов I класса автомобилями-самосвалами грузоподъемностью до 30 т по дорогам с усовершенствованным (асфальтобетонным, цементобетонным, железобетонным, обработанным органическим вяжущим) дорожным покрытием на расстояние 140 км | E3: Нерудка | F3: 1т груза | G3: 269 | H3: 900 | I3: =H3*G3 -> 242100 | K3: ВОР 01-01-01, логистика; Источник: 03-01/07.21П-ООС.ТЧ. л 47 (Файл: 03-01_07.21П- ПЗУ.pdf, стр.: 178 179)
A4: ВОР 4 | B4: Перевозка грузов I класса автомобилями-самосвалами грузоподъемностью до 15 т по дорогам с усовершенствованным (асфальтобетонным, цементобетонным, железобетонным, обработанным органическим вяжущим) дорожным покрытием на расстояние 140 км | E4: Нерудка | F4: 1т груза | G4: 26796.8 | H4: 900 | I4: =H4*G4 -> 24117120 | K4: ВОР 01-01-01, логистика; Источник: 03-01/07.21П-ПОС.ТЧ. Приложение Д л. 179,187 (Файл: 03-01_07.21П-КР.pdf, стр.: 179)
A5: ВОР 3 | B5: Перевозка грузов I класса автомобилями-самосвалами грузоподъемностью до 15 т по дорогам с усовершенствованным (асфальтобетонным, цементобетонным, железобетонным, обработанным органическим вяжущим) дорожным покрытием на расстояние 140 км | E5: Нерудка | F5: 1т груза | G5: 112.704 | H5: 900 | I5: =H5*G5 -> 101433.6 | K5: ВОР 04-01-01, логистика; Источник: 03-01/07.21П-ИОС.1.5. л.10 (Файл: 03-01_07.21П- ИОС.1.5.pdf, стр.: 10)
A6: ВОР 4 | B6: Перевозка грузов I класса автомобилями-самосвалами грузоподъемностью до 15 т по дорогам с усовершенствованным (асфальтобетонным, цементобетонным, железобетонным, обработанным органическим вяжущим) дорожным покрытием на расстояние 140 км | E6: Нерудка | F6: 1т груза | G6: 169.6 | H6: 900 | I6: =H6*G6 -> 152640 | K6: ВОР 06-01-01, логистика; Источник: 03-01/07.21П-ПОС.ТЧ. Приложение Д. л. 179 (Файл: 03-01_07.21П-ПОС.pdf, стр.: 1)
A7: ВОР 16 | B7: Перевозка грузов I класса автомобилями-самосвалами грузоподъемностью до 15 т по дорогам с усовершенствованным (асфальтобетонным, цементобетонным, железобетонным, обработанным органическим вяжущим) дорожным покрытием на расстояние 140 км | E7: Нерудка | F7: 1т груза | G7: 851.2 | H7: 900 | I7: =H7*G7 -> 766080 | K7: ВОР 06-01-01, логистика; Источник: 03-01/07.21П-ПОС.ТЧ. Приложение Д. л. 179 (Файл: 03-01_07.21П-ПОС.pdf, стр.: 1)
A8: ВОР 29 | B8: Перевозка грузов I класса автомобилями-самосвалами грузоподъемностью до 15 т по дорогам с усовершенствованным (асфальтобетонным, цементобетонным, железобетонным, обработанным органическим вяжущим) дорожным покрытием на расстояние 140 км | E8: Нерудка | F8: 1т груза | G8: 76.8 | H8: 900 | I8: =H8*G8 -> 69120 | K8: ВОР 06-01-01, логистика; Источник: 03-01/07.21П-ПОС.ТЧ. Приложение Д. л. 180 (Файл: 03-01_07.21П-ПОС.pdf, стр.: 1)
A9: ВОР 4 | B9: Перевозка грузов I класса автомобилями-самосвалами грузоподъемностью до 15 т по дорогам с усовершенствованным (асфальтобетонным, цементобетонным, железобетонным, обработанным органическим вяжущим) дорожным покрытием на расстояние 140 км | E9: Нерудка | F9: 1т груза | G9: 228.8 | H9: 900 | I9: =H9*G9 -> 205920 | K9: ВОР 06-01-02, логистика; Источник: 03-01/07.21П-ПОС.ТЧ. Приложение Д. л. 186 (Файл: 03-01_07.21П-ПОС.pdf, стр.: 1)
A10: ВОР 15 | B10: Перевозка грузов I класса автомобилями-самосвалами грузоподъемностью до 15 т по дорогам с усовершенствованным (асфальтобетонным, цементобетонным, железобетонным, обработанным органическим вяжущим) дорожным покрытием на расстояние 140 км | E10: Нерудка | F10: 1т груза | G10: 30.4 | H10: 900 | I10: =H10*G10 -> 27360 | K10: ВОР 06-01-02, логистика; Источник: 03-01/07.21П-ПОС.ТЧ. Приложение Д. л. 181-182 (Файл: 03-01_07.21П-ПОС.pdf, стр.: 1)
A11: ВОР 25 | B11: Перевозка грузов I класса автомобилями-самосвалами грузоподъемностью до 15 т по дорогам с усовершенствованным (асфальтобетонным, цементобетонным, железобетонным, обработанным органическим вяжущим) дорожным покрытием на расстояние 140 км | E11: Нерудка | F11: 1т груза | G11: 625.6 | H11: 900 | I11: =H11*G11 -> 563040 | K11: ВОР 06-01-02, логистика; Источник: 03-01/07.21П-ПОС.ТЧ. Приложение Д. л. 186 (Файл: 03-01_07.21П-ПОС.pdf, стр.: 1)
A12: ВОР 37 | B12: Перевозка грузов I класса автомобилями-самосвалами грузоподъемностью до 15 т по дорогам с усовершенствованным (асфальтобетонным, цементобетонным, железобетонным, обработанным органическим вяжущим) дорожным покрытием на расстояние 140 км | E12: Нерудка | F12: 1т груза | G12: 104 | H12: 900 | I12: =H12*G12 -> 93600 | K12: ВОР 06-01-02, логистика; Источник: 03-01/07.21П-ПОС.ТЧ. Приложение Д. л. 181-182 (Файл: 03-01_07.21П-ПОС.pdf, стр.: 1)
A13: ВОР 52 | B13: Перевозка грузов I класса автомобилями-самосвалами грузоподъемностью до 15 т по дорогам с усовершенствованным (асфальтобетонным, цементобетонным, железобетонным, обработанным органическим вяжущим) дорожным покрытием на расстояние 140 км | E13: Нерудка | F13: 1т груза | G13: 1510.4 | H13: 900 | I13: =H13*G13 -> 1359360 | K13: ВОР 06-01-02, логистика; Источник: 03-01/07.21П-ПОС.ТЧ. Приложение Д. л. 186 (Файл: 03-01_07.21П-ПОС.pdf, стр.: 1)
A14: ВОР 65 | B14: Перевозка грузов I класса автомобилями-самосвалами грузоподъемностью до 15 т по дорогам с усовершенствованным (асфальтобетонным, цементобетонным, железобетонным, обработанным органическим вяжущим) дорожным покрытием на расстояние 140 км | E14: Нерудка | F14: 1т груза | G14: 329.6 | H14: 900 | I14: =H14*G14 -> 296640 | K14: ВОР 06-01-02, логистика; Источник: 03-01/07.21П-ПОС.ТЧ. Приложение Д. л. 184 (Файл: 03-01_07.21П-ПОС.pdf, стр.: 1)
... A17: ВОР 26 | B17: Перевозка грузов I класса автомобилями-самосвалами грузоподъемностью до 15 т по дорогам с усовершенствованным (асфальтобетонным, цементобетонным, железобетонным, обработанным органическим вяжущим) дорожным покрытием на расстояние 140 км | E17: Нерудка | F17: 1т груза | G17: 124.03 | H17: 900 | I17: =H17*G17 -> 111627 | K17: ВОР 07-01-04, логистика; Источник: 03-01/07.21П-ИОС.1.4.ГЧ л.2 (Файл: 03-01_07.21П- ИОС.1.4.pdf, стр.: 18 19 20 21)
A18: 5.1. | B18: СИСТЕМА ЭЛЕКТРОСНАБЖЕНИЯ
B19: Электрооборудование 03-01/07.21П-ИОС-1.1.СО
A20: 1 | B20: ЩИТОВОЕ ОБОРУДОВАНИЕ
B21: Главный распределительный щит, ГРЩ-1 | C21: Согласно схеме см. ГЧ | E21: Россия | F21: компл. | G21: 1 | H21: 959419.25 | I21: =H21*G21 -> 959419.25
B22: Главный распределительный щит, ГРЩ-2 | C22: Согласно схеме см. ГЧ | E22: Россия | F22: компл. | G22: 1 | H22: 2812830 | I22: =H22*G22 -> 2812830
B23: Щит силовой навесного исполнения, ЩС1 | C23: Согласно схеме см. ГЧ | E23: Россия | F23: компл. | G23: 1 | H23: 66620.7 | I23: =H23*G23 -> 66620.7
B24: Щит силовой навесного исполнения, ЩС2 | C24: Согласно схеме см. ГЧ | E24: Россия | F24: компл. | G24: 1 | H24: 94135.83 | I24: =H24*G24 -> 94135.83
B25: Щит силовой навесного исполнения, ЩС3 | C25: Согласно схеме см. ГЧ | E25: Россия | F25: компл. | G25: 1 | H25: 40035.53 | I25: =H25*G25 -> 40035.53
B26: Щит силовой навесного исполнения, ЩС4 | C26: Согласно схеме см. ГЧ | E26: Россия | F26: компл. | G26: 1 | H26: 46940.94 | I26: =H26*G26 -> 46940.94
B27: Щит силовой навесного исполнения, ЩС5 | C27: Согласно схеме см. ГЧ | E27: Россия | F27: компл. | G27: 1 | H27: 53529.39 | I27: =H27*G27 -> 53529.39
B28: Щит силовой навесного исполнения, ЩС6 | C28: Согласно схеме см. ГЧ | E28: Россия | F28: компл. | G28: 1 | H28: 56081.52 | I28: =H28*G28 -> 56081.52
B29: Щит силовой навесного исполнения, ЩС7 | C29: Согласно схеме см. ГЧ | E29: Россия | F29: компл. | G29: 1 | H29: 47192.31 | I29: =H29*G29 -> 47192.31
B30: Щит силовой навесного исполнения, ЩС8 | C30: Согласно схеме см. ГЧ | E30: Россия | F30: компл. | G30: 1 | H30: 53529.39 | I30: =H30*G30 -> 53529.39
B31: Щит силовой навесного исполнения, ЩС9 | C31: Согласно схеме см. ГЧ | E31: Россия | F31: компл. | G31: 1 | H31: 40451.43 | I31: =H31*G31 -> 40451.43
B32: Щит силовой навесного исполнения, ЩС10 | C32: Согласно схеме см. ГЧ | E32: Россия | F32: компл. | G32: 1 | H32: 28839.95 | I32: =H32*G32 -> 28839.95
... B48: Конденсаторная установка | C48: КРМ-0,4-25-5 У3 | E48: Россия | F48: компл. | G48: 1 | H48: 73170.72 | I48: =H48*G48 -> 73170.72
A49: 2 | B49: ЭЛЕКТРОУСТАНОВОЧНЫЕ ИЗДЕЛИЯ
B50: Розетка комп. одинарная двухполюсная с защитным контактом, IP20 | E50: Россия | F50: шт. | G50: 107 | H50: 639.2556 | I50: =H50*G50 -> 68400.349 | K50: отличительной расцветки
B51: Розетка одинарная двухполюсная с защитным контактом, IP20 | E51: Россия | F51: шт. | G51: 152 | H51: 165.066 | I51: =H51*G51 -> 25090.032
B52: Розетка одинарная двухполюсная с защитным контактом, IP44 | E52: Россия | F52: шт. | G52: 150 | H52: 286.6146 | I52: =H52*G52 -> 42992.19
B53: Коробка для э/у изделий 1-постовая | E53: Россия | F53: шт. | G53: 409 | H53: 11.0532 | I53: =H53*G53 -> 4520.7588
B54: Розетка наружной установки 380В | E54: Россия | F54: шт. | G54: 4 | H54: 1680 | I54: =H54*G54 -> 6720
B55: Коробка ответвительная скрытой установки | E55: Россия | F55: шт. | G55: 740 | H55: 79.4342 | I55: =H55*G55 -> 58781.308
A56: 3 | B56: КАБЕЛЬНАЯ ПРОДУКЦИЯ | K56: в СО этот раздел № 4 (в оригинале номер 3 пропущен)
B57: Кабель с медными жилами, с ПВХ изоляцией | C57: ВВГнг(А)-HF 3х2,5 | E57: Россия | F57: м | G57: 11406 | H57: 130 | I57: =H57*G57 -> 1482780
B58: Кабель с медными жилами, с ПВХ изоляцией | C58: ВВГнг(А)-HF 3х4 | E58: Россия | F58: м | G58: 404 | H58: 250 | I58: =H58*G58 -> 101000
B59: Кабель с медными жилами, с ПВХ изоляцией | C59: ВВГнг(А)-HF 3х6 | E59: Россия | F59: м | G59: 177 | H59: 360 | I59: =H59*G59 -> 63720
B60: Кабель с медными жилами, с ПВХ изоляцией | C60: ВВГнг(А)-HF 3х10 | E60: Россия | F60: м | G60: 103 | H60: 520 | I60: =H60*G60 -> 53560
B61: Кабель с медными жилами, с ПВХ изоляцией | C61: ВВГнг(А)-HF 5х2,5 | E61: Россия | F61: м | G61: 1156 | H61: 250 | I61: =H61*G61 -> 289000
B62: Кабель с медными жилами, с ПВХ изоляцией | C62: ВВГнг(А)-HF 5х4 | E62: Россия | F62: м | G62: 1960 | H62: 400 | I62: =H62*G62 -> 784000
B63: Кабель с медными жилами, с ПВХ изоляцией | C63: ВВГнг(А)-HF 5х25 | E63: Россия | F63: м | G63: 297 | H63: 2830 | I63: =H63*G63 -> 840510
B64: Кабель с медными жилами, с ПВХ изоляцией | C64: ВВГнг(А)-HF 5х16 | E64: Россия | F64: м | G64: 2356 | H64: 1780 | I64: =H64*G64 -> 4193680
B65: Кабель с медными жилами, с ПВХ изоляцией | C65: ВВГнг(А)-HF 5х6 | E65: Россия | F65: м | G65: 722 | H65: 580 | I65: =H65*G65 -> 418760
B66: Кабель с медными жилами, с ПВХ изоляцией | C66: ВВГнг(А)-HF 5х10 | E66: Россия | F66: м | G66: 716 | H66: 1165 | I66: =H66*G66 -> 834140
B67: Кабель с медными жилами, с ПВХ изоляцией | C67: ВВГнг(А)-HF 5х70 | E67: Россия | F67: м | G67: 150 | H67: 7065 | I67: =H67*G67 -> 1059750
B68: Кабель с медными жилами, с ПВХ изоляцией | C68: ВВГнг(А)-HF 5х150 | E68: Россия | F68: м | G68: 292 | H68: 17255 | I68: =H68*G68 -> 5038460
... B73: Кабель с медными жилами, с ПВХ изоляцией | C73: ВВГнг(A)-FRHF 5х25 | E73: Россия | F73: м | G73: 160 | H73: 2716 | I73: =H73*G73 -> 434560
A74: 4 | B74: КАБЕЛЕНЕСУЩИЕ СИСТЕМЫ | K74: в СО этот раздел № 5 (в оригинале номер 3 пропущен)
B75: Труба ПВХ гофрированная Ø25мм | C75: 91925 | E75: Торговая сеть | F75: м | G75: 6636 | H75: 35.075 | I75: =H75*G75 -> 232757.7
B76: Труба ПВХ гофрированная Ø40мм | C76: 91940 | E76: Торговая сеть | F76: м | G76: 1540 | H76: 70.6014 | I76: =H76*G76 -> 108726.16
B77: Лоток неперфорированный 200х100х3000мм с крышкой | C77: 35103+35524 | E77: Торговая сеть | F77: шт. | G77: 139 | H77: 4937.6328 | I77: =H77*G77 -> 686330.96
B78: Лоток неперфорированный 300х100х3000мм с крышкой | C78: 35104+35525 | E78: Торговая сеть | F78: шт. | G78: 139 | H78: 7326.8442 | I78: =H78*G78 -> 1018431.3
B79: Швеллер перфорированный П-образный 40х20х2, L=1м | E79: Торговая сеть | F79: шт. | G79: 556 | H79: 593.1518 | I79: =H79*G79 -> 329792.4
B80: Шпилька M8 L=1000мм | F80: шт. | G80: 1112 | H80: 177.51 | I80: =H80*G80 -> 197391.12
B81: Клипсы Ø25мм для трубы ПВХ Ø25мм (600шт. в упаковке) | F81: уп. | G81: 12 | H81: 3660 | I81: =H81*G81 -> 43920
B82: Клипсы Ø40мм для трубы ПВХ Ø40мм (600шт. в упаковке) | F82: уп. | G82: 3 | H82: 12297.6 | I82: =H82*G82 -> 36892.8
A83: 5 | B83: УРАВНИВАНИЕ ПОТЕНЦИАЛОВ | K83: в СО этот раздел № 6 (в оригинале номер 3 пропущен)
B84: Провод с медными жилами, на напряжение до 0,66кВ | C84: ПуГВнг(А)-LSLTx | D84: -
B85: 1х25 | D85: - | E85: Торговая сеть | F85: м | G85: 1991 | H85: 366.4392 | I85: =H85*G85 -> 729580.45
B86: 1х6 | D86: - | E86: Торговая сеть | F86: м | G86: 3405 | H86: 85.9612 | I86: =H86*G86 -> 292697.89
B87: Шина дополнительного уравнивания потенциалов (ШДУП) в составе: | F87: компл. | G87: 34 | H87: =I88+I89 -> 1393.2464 | I87: =H87*G87-I88-I89 -> 45977.131
B88: - шина в изоляторе 8х12 групп 12 ответвлений | F88: шт. | G88: 2 | H88: 371.8072 | I88: =H88*G88 -> 743.6144 | K88: макс. сечение подключаемого проводника 16мм2
B89: - вводная клемма для модульного оборудования, изолированная с винтовым зажимом 4-25мм2 | F89: шт. | G89: 4 | H89: 162.408 | I89: =H89*G89 -> 649.632 | K89: для подключения проводника 25мм2 к шине
B90: Полоса стальная оцинкованная 40х5мм | E90: Производство Россия | F90: м | G90: 500 | H90: 471.9326 | I90: =H90*G90 -> 235966.3 | K90: заземление лифт. шахт и иных помещений (ГРЩ, бойлерная, водом. узел)
A91: 6 | B91: ЗАЩИТНЫЕ СРЕДСТВА | K91: в СО этот раздел № 7 (в оригинале номер 3 пропущен)
B92: Перчатки диэлектрические, ~U до 1кВ | C92: ТУ 38305-05-257-89 | E92: Торговая сеть | F92: шт. | G92: 2 | H92: 838.9208 | I92: =H92*G92 -> 1677.8416
B93: Диэлектрические боты, ~U до 1кВ | E93: Торговая сеть | F93: пара | G93: 2 | H93: 1118.7156 | I93: =H93*G93 -> 2237.4312
B94: Ковер диэлектрический 900х900, ~U до 20кВ | C94: ГОСТ 4997-75 | E94: Торговая сеть | F94: шт. | G94: 5 | H94: 1300.6542 | I94: =H94*G94 -> 6503.271
B95: Комплект плакатов по электробезопасности | E95: Торговая сеть | F95: компл. | G95: 2 | H95: 804.224 | I95: =H95*G95 -> 1608.448
B96: Электропассатижи, ~U до 1кВ | E96: Торговая сеть | F96: шт. | G96: 2 | H96: 741.1988 | I96: =H96*G96 -> 1482.3976
B97: Клещи токоизмерительные | C97: М266 | E97: Торговая сеть | F97: шт. | G97: 1 | H97: 2243.2628 | I97: =H97*G97 -> 2243.2628
B98: Огнетушитель | C98: ОП-5 | E98: Торговая сеть | F98: шт. | G98: 1 | H98: 2870.9284 | I98: =H98*G98 -> 2870.9284
B99: Штанга изолирующая | C99: ШО-1 | E99: Торговая сеть | F99: шт. | G99: 1 | H99: 429.0618 | I99: =H99*G99 -> 429.0618
B100: Очки защитные | E100: Торговая сеть | F100: шт. | G100: 2 | H100: 118.523 | I100: =H100*G100 -> 237.046
B101: Указатель напряжения до 1000В | E101: Торговая сеть | F101: шт. | G101: 2 | H101: 266.204 | I101: =H101*G101 -> 532.408
A102: 7 | B102: ОБОРУДОВАНИЕ И МАТЕРИАЛЫ | K102: в СО этот раздел № 8 (в оригинале номер 3 пропущен)
B103: Метизы | E103: Торговая сеть | F103: кг | G103: 40 | H103: 220 | I103: =H103*G103 -> 8800
B104: Плита из минерал. волокна с огнестойким покрытием, размером 1000х500х52 | E104: Торговая сеть | F104: шт. | G104: 100 | H104: 8453.624 | I104: =H104*G104 -> 845362.4
B105: Герметик огнезащитный, ведро 20кг | E105: Торговая сеть | F105: шт. | G105: 18 | H105: 30672.435 | I105: =H105*G105 -> 552103.83
B106: Труба стальная оцинкованная Ø50мм | C106: ГОСТ 3262-75 | E106: Производство Россия | F106: м | G106: 75 | H106: 850 | I106: =H106*G106 -> 63750
B107: Огнестойкая пена | E107: Торговая сеть | F107: шт. | G107: 50 | H107: 630.923 | I107: =H107*G107 -> 31546.15
B108: Электрическое освещение 03-01/07.21П-ИОС-1.2.СО
A109: 1 | B109: ЩИТОВОЕ ОБОРУДОВАНИЕ
B110: Щит рабочего освещения навесного исполнения, ЩО1 | C110: Согласно схеме см. ГЧ | E110: Россия | F110: компл. | G110: 1 | H110: 41771.22 | I110: =H110*G110 -> 41771.22
B111: Щит рабочего освещения навесного исполнения, ЩО2 | C111: Согласно схеме см. ГЧ | E111: Россия | F111: компл. | G111: 1 | H111: 6967.73 | I111: =H111*G111 -> 6967.73
B112: Щит рабочего освещения навесного исполнения, ЩО3 | C112: Согласно схеме см. ГЧ | E112: Россия | F112: компл. | G112: 1 | H112: 9062.58 | I112: =H112*G112 -> 9062.58
B113: Щит рабочего освещения навесного исполнения, ЩО4 | C113: Согласно схеме см. ГЧ | E113: Россия | F113: компл. | G113: 1 | H113: 11739.06 | I113: =H113*G113 -> 11739.06
B114: Щит рабочего освещения навесного исполнения, ЩО5 | C114: Согласно схеме см. ГЧ | E114: Россия | F114: компл. | G114: 1 | H114: 11739.06 | I114: =H114*G114 -> 11739.06
B115: Щит рабочего освещения навесного исполнения, ЩО6 | C115: Согласно схеме см. ГЧ | E115: Россия | F115: компл. | G115: 1 | H115: 8621.06 | I115: =H115*G115 -> 8621.06
B116: Щит рабочего освещения навесного исполнения, ЩО7 | C116: Согласно схеме см. ГЧ | E116: Россия | F116: компл. | G116: 1 | H116: 8621.06 | I116: =H116*G116 -> 8621.06
B117: Щит рабочего освещения навесного исполнения, ЩО8 | C117: Согласно схеме см. ГЧ | E117: Россия | F117: компл. | G117: 1 | H117: 8621.06 | I117: =H117*G117 -> 8621.06
B118: Щит рабочего освещения навесного исполнения, ЩО9 | C118: Согласно схеме см. ГЧ | E118: Россия | F118: компл. | G118: 1 | H118: 9062.58 | I118: =H118*G118 -> 9062.58
B119: Щит рабочего освещения навесного исполнения, ЩО10 | C119: Согласно схеме см. ГЧ | E119: Россия | F119: компл. | G119: 1 | H119: 8621.06 | I119: =H119*G119 -> 8621.06
B120: Щит аварийного освещения навесного исполнения, ЩАО1 | C120: Согласно схеме см. ГЧ | E120: Россия | F120: компл. | G120: 1 | H120: 23241.3 | I120: =H120*G120 -> 23241.3
B121: Щит аварийного освещения навесного исполнения, ЩАО2 | C121: Согласно схеме см. ГЧ | E121: Россия | F121: компл. | G121: 1 | H121: 19299.08 | I121: =H121*G121 -> 19299.08
...

Sheet НЕТ В СО (из ВОРов)
A1: ЧТО ЕСТЬ В ВОРах, НО ОТСУТСТВУЕТ В СПЕЦИФИКАЦИЯХ (СО)
A2: Правило: позиция есть и в СО, и в ВОРе — берём как в СО. В СО нет, а в ВОРе есть — берём по ВОРу. Складывать СО и ВОР нельзя.
A3: Здесь только второе — то, чего в СО нет вообще. Это то, что придётся закупать и расценивать сверх спецификаций.
A4: Кол-во, цена и сумма подтянуты формулами с листа «Спецификация» — править их надо там, здесь пересчитается само. Колонка J — номер строки-источника.
A5: Блок ВОР 02-01-11 (ТХ.2) на листе «Спецификация» сокращён с 369 строк до 3: остальные 366 были дублями ТХ.2.СО. Их цены (257 100 ₽) перенесены на строки ТХ.2.СО, ИТОГО книги не изменилось.
A7: № | B7: Раздел / дисциплина ВОР | C7: № по ВОР | D7: Наименование | E7: Тип, марка | F7: Ед. изм. | G7: Кол-во | H7: Цена, руб. с НДС | I7: Сумма, руб. с НДС | J7: Строка в «Спецификации» | K7: Статус цены | L7: Примечание в книге
A8: Логистика — перевозка грузов (из ВОРов) (15 поз.)
A9: 1 | B9: Логистика — перевозка грузов (из ВОРов) | C9: ВОР 20 | D9: Перевозка грузов I класса автомобилями-самосвалами грузоподъемностью до 30 т по дорогам с усовершенствованным (асфальтобетонным, цементобетонным, железобетонным, обработанным органическим вяжущим) дорожным покрытием на расстояние 140 км | E9: 03-01/07.21П-ООС.ТЧ. л 47 (Файл: 03-01_07.21П- ПЗУ.pdf, стр.: 178 179) | F9: 1т груза | G9: =Спецификация!G3 -> 269 | H9: =Спецификация!H3 -> 900 | I9: =Спецификация!I3 -> 242100 | J9: 3 | K9: =IF(H9=0,"НЕТ ЦЕНЫ","проценено") -> проценено | L9: ВОР 01-01-01, логистика
A10: 2 | B10: Логистика — перевозка грузов (из ВОРов) | C10: ВОР 4 | D10: Перевозка грузов I класса автомобилями-самосвалами грузоподъемностью до 15 т по дорогам с усовершенствованным (асфальтобетонным, цементобетонным, железобетонным, обработанным органическим вяжущим) дорожным покрытием на расстояние 140 км | E10: 03-01/07.21П-ПОС.ТЧ. Приложение Д л. 179,187 (Файл: 03-01_07.21П-КР.pdf, стр.: 179) | F10: 1т груза | G10: =Спецификация!G4 -> 26796.8 | H10: =Спецификация!H4 -> 900 | I10: =Спецификация!I4 -> 24117120 | J10: 4 | K10: =IF(H10=0,"НЕТ ЦЕНЫ","проценено") -> проценено | L10: ВОР 01-01-01, логистика
A11: 3 | B11: Логистика — перевозка грузов (из ВОРов) | C11: ВОР 3 | D11: Перевозка грузов I класса автомобилями-самосвалами грузоподъемностью до 15 т по дорогам с усовершенствованным (асфальтобетонным, цементобетонным, железобетонным, обработанным органическим вяжущим) дорожным покрытием на расстояние 140 км | E11: 03-01/07.21П-ИОС.1.5. л.10 (Файл: 03-01_07.21П- ИОС.1.5.pdf, стр.: 10) | F11: т груз а | G11: =Спецификация!G5 -> 112.704 | H11: =Спецификация!H5 -> 900 | I11: =Спецификация!I5 -> 101433.6 | J11: 5 | K11: =IF(H11=0,"НЕТ ЦЕНЫ","проценено") -> проценено | L11: ВОР 04-01-01, логистика
A12: 4 | B12: Логистика — перевозка грузов (из ВОРов) | C12: ВОР 4 | D12: Перевозка грузов I класса автомобилями-самосвалами грузоподъемностью до 15 т по дорогам с усовершенствованным (асфальтобетонным, цементобетонным, железобетонным, обработанным органическим вяжущим) дорожным покрытием на расстояние 140 км | E12: 03-01/07.21П-ПОС.ТЧ. Приложение Д. л. 179 (Файл: 03-01_07.21П-ПОС.pdf, стр.: 1) | F12: 1т груза | G12: =Спецификация!G6 -> 169.6 | H12: =Спецификация!H6 -> 900 | I12: =Спецификация!I6 -> 152640 | J12: 6 | K12: =IF(H12=0,"НЕТ ЦЕНЫ","проценено") -> проценено | L12: ВОР 06-01-01, логистика
A13: 5 | B13: Логистика — перевозка грузов (из ВОРов) | C13: ВОР 16 | D13: Перевозка грузов I класса автомобилями-самосвалами грузоподъемностью до 15 т по дорогам с усовершенствованным (асфальтобетонным, цементобетонным, железобетонным, обработанным органическим вяжущим) дорожным покрытием на расстояние 140 км | E13: 03-01/07.21П-ПОС.ТЧ. Приложение Д. л. 179 (Файл: 03-01_07.21П-ПОС.pdf, стр.: 1) | F13: 1т груза | G13: =Спецификация!G7 -> 851.2 | H13: =Спецификация!H7 -> 900 | I13: =Спецификация!I7 -> 766080 | J13: 7 | K13: =IF(H13=0,"НЕТ ЦЕНЫ","проценено") -> проценено | L13: ВОР 06-01-01, логистика
A14: 6 | B14: Логистика — перевозка грузов (из ВОРов) | C14: ВОР 29 | D14: Перевозка грузов I класса автомобилями-самосвалами грузоподъемностью до 15 т по дорогам с усовершенствованным (асфальтобетонным, цементобетонным, железобетонным, обработанным органическим вяжущим) дорожным покрытием на расстояние 140 км | E14: 03-01/07.21П-ПОС.ТЧ. Приложение Д. л. 180 (Файл: 03-01_07.21П-ПОС.pdf, стр.: 1) | F14: 1т груза | G14: =Спецификация!G8 -> 76.8 | H14: =Спецификация!H8 -> 900 | I14: =Спецификация!I8 -> 69120 | J14: 8 | K14: =IF(H14=0,"НЕТ ЦЕНЫ","проценено") -> проценено | L14: ВОР 06-01-01, логистика
A15: 7 | B15: Логистика — перевозка грузов (из ВОРов) | C15: ВОР 4 | D15: Перевозка грузов I класса автомобилями-самосвалами грузоподъемностью до 15 т по дорогам с усовершенствованным (асфальтобетонным, цементобетонным, железобетонным, обработанным органическим вяжущим) дорожным покрытием на расстояние 140 км | E15: 03-01/07.21П-ПОС.ТЧ. Приложение Д. л. 186 (Файл: 03-01_07.21П-ПОС.pdf, стр.: 1) | F15: 1т | G15: =Спецификация!G9 -> 228.8 | H15: =Спецификация!H9 -> 900 | I15: =Спецификация!I9 -> 205920 | J15: 9 | K15: =IF(H15=0,"НЕТ ЦЕНЫ","проценено") -> проценено | L15: ВОР 06-01-02, логистика
A16: 8 | B16: Логистика — перевозка грузов (из ВОРов) | C16: ВОР 15 | D16: Перевозка грузов I класса автомобилями-самосвалами грузоподъемностью до 15 т по дорогам с усовершенствованным (асфальтобетонным, цементобетонным, железобетонным, обработанным органическим вяжущим) дорожным покрытием на расстояние 140 км | E16: 03-01/07.21П-ПОС.ТЧ. Приложение Д. л. 181-182 (Файл: 03-01_07.21П-ПОС.pdf, стр.: 1) | F16: 1т груза | G16: =Спецификация!G10 -> 30.4 | H16: =Спецификация!H10 -> 900 | I16: =Спецификация!I10 -> 27360 | J16: 10 | K16: =IF(H16=0,"НЕТ ЦЕНЫ","проценено") -> проценено | L16: ВОР 06-01-02, логистика
A17: 9 | B17: Логистика — перевозка грузов (из ВОРов) | C17: ВОР 25 | D17: Перевозка грузов I класса автомобилями-самосвалами грузоподъемностью до 15 т по дорогам с усовершенствованным (асфальтобетонным, цементобетонным, железобетонным, обработанным органическим вяжущим) дорожным покрытием на расстояние 140 км | E17: 03-01/07.21П-ПОС.ТЧ. Приложение Д. л. 186 (Файл: 03-01_07.21П-ПОС.pdf, стр.: 1) | F17: 1т | G17: =Спецификация!G11 -> 625.6 | H17: =Спецификация!H11 -> 900 | I17: =Спецификация!I11 -> 563040 | J17: 11 | K17: =IF(H17=0,"НЕТ ЦЕНЫ","проценено") -> проценено | L17: ВОР 06-01-02, логистика
A18: 10 | B18: Логистика — перевозка грузов (из ВОРов) | C18: ВОР 37 | D18: Перевозка грузов I класса автомобилями-самосвалами грузоподъемностью до 15 т по дорогам с усовершенствованным (асфальтобетонным, цементобетонным, железобетонным, обработанным органическим вяжущим) дорожным покрытием на расстояние 140 км | E18: 03-01/07.21П-ПОС.ТЧ. Приложение Д. л. 181-182 (Файл: 03-01_07.21П-ПОС.pdf, стр.: 1) | F18: 1т груза | G18: =Спецификация!G12 -> 104 | H18: =Спецификация!H12 -> 900 | I18: =Спецификация!I12 -> 93600 | J18: 12 | K18: =IF(H18=0,"НЕТ ЦЕНЫ","проценено") -> проценено | L18: ВОР 06-01-02, логистика
A19: 11 | B19: Логистика — перевозка грузов (из ВОРов) | C19: ВОР 52 | D19: Перевозка грузов I класса автомобилями-самосвалами грузоподъемностью до 15 т по дорогам с усовершенствованным (асфальтобетонным, цементобетонным, железобетонным, обработанным органическим вяжущим) дорожным покрытием на расстояние 140 км | E19: 03-01/07.21П-ПОС.ТЧ. Приложение Д. л. 186 (Файл: 03-01_07.21П-ПОС.pdf, стр.: 1) | F19: 1т груза | G19: =Спецификация!G13 -> 1510.4 | H19: =Спецификация!H13 -> 900 | I19: =Спецификация!I13 -> 1359360 | J19: 13 | K19: =IF(H19=0,"НЕТ ЦЕНЫ","проценено") -> проценено | L19: ВОР 06-01-02, логистика
A20: 12 | B20: Логистика — перевозка грузов (из ВОРов) | C20: ВОР 65 | D20: Перевозка грузов I класса автомобилями-самосвалами грузоподъемностью до 15 т по дорогам с усовершенствованным (асфальтобетонным, цементобетонным, железобетонным, обработанным органическим вяжущим) дорожным покрытием на расстояние 140 км | E20: 03-01/07.21П-ПОС.ТЧ. Приложение Д. л. 184 (Файл: 03-01_07.21П-ПОС.pdf, стр.: 1) | F20: 1т груза | G20: =Спецификация!G14 -> 329.6 | H20: =Спецификация!H14 -> 900 | I20: =Спецификация!I14 -> 296640 | J20: 14 | K20: =IF(H20=0,"НЕТ ЦЕНЫ","проценено") -> проценено | L20: ВОР 06-01-02, логистика
... A23: 15 | B23: Логистика — перевозка грузов (из ВОРов) | C23: ВОР 26 | D23: Перевозка грузов I класса автомобилями-самосвалами грузоподъемностью до 15 т по дорогам с усовершенствованным (асфальтобетонным, цементобетонным, железобетонным, обработанным органическим вяжущим) дорожным покрытием на расстояние 140 км | E23: 03-01/07.21П-ИОС.1.4.ГЧ л.2 (Файл: 03-01_07.21П- ИОС.1.4.pdf, стр.: 18 19 20 21) | F23: 1т груза | G23: =Спецификация!G17 -> 124.03 | H23: =Спецификация!H17 -> 900 | I23: =Спецификация!I17 -> 111627 | J23: 17 | K23: =IF(H23=0,"НЕТ ЦЕНЫ","проценено") -> проценено | L23: ВОР 07-01-04, логистика
D24: Итого по разделу | I24: =SUM(I9:I23) -> 35451481
A26: Позиции из ВОРов, вставленные в разделы СО (ИОС) (46 поз.)
A27: 16 | B27: Позиции из ВОРов, вставленные в разделы СО (ИОС) | C27: ВОР 154 | D27: Умывальник полуфарфоровый и фарфоровый прямоугольный с кронштейнами, сифоном бутылочным из латуни, выпуском, одно отверстие под смеситель, смеситель с центральным подводом, набортный с двумя рукоятями, излив с развальцованным носиком, вынос излива 280 мм, размеры 450x330x150 мм | E27: 03-01/07.21П-ИОС 2.1.ГЧ Спецификация (Файл: 03- 01_07.21П-ИОС.2.pdf стр.: 1 2 3 4 5 6) | F27: к-т | G27: =Спецификация!G384 -> 68 | H27: =Спецификация!H384 -> 0 | I27: =Спецификация!I384 -> 0 | J27: 384 | K27: =IF(H27=0,"НЕТ ЦЕНЫ","проценено") -> НЕТ ЦЕНЫ | L27: ВОР, нет в СО
A28: 17 | B28: Позиции из ВОРов, вставленные в разделы СО (ИОС) | C28: ВОР 156 | D28: Унитаз керамический напольный в комплекте с бачком, с косым выпуском, размеры 360x620x765 мм | E28: 03-01/07.21П-ИОС 2.1.ГЧ Спецификация (Файл: 03- 01_07.21П-ИОС.2.pdf стр.: 1 2 3 4 5 6) | F28: к-т | G28: =Спецификация!G385 -> 51 | H28: =Спецификация!H385 -> 0 | I28: =Спецификация!I385 -> 0 | J28: 385 | K28: =IF(H28=0,"НЕТ ЦЕНЫ","проценено") -> НЕТ ЦЕНЫ | L28: ВОР, нет в СО
A29: 18 | B29: Позиции из ВОРов, вставленные в разделы СО (ИОС) | C29: ВОР 158 | D29: Писсуар настенный керамический, подвод воды скрытый, вход слива скрытый, размеры 275x310x540 мм, с краном нажимным, центральным подводом, набортный, размеры 215x104x50 мм | E29: 03-01/07.21П-ИОС 2.1.ГЧ Спецификация (Файл: 03- 01_07.21П-ИОС.2.pdf стр.: 1 2 3 4 5 6) | F29: шт. | G29: =Спецификация!G386 -> 10 | H29: =Спецификация!H386 -> 0 | I29: =Спецификация!I386 -> 0 | J29: 386 | K29: =IF(H29=0,"НЕТ ЦЕНЫ","проценено") -> НЕТ ЦЕНЫ | L29: ВОР, нет в СО
A30: 19 | B30: Позиции из ВОРов, вставленные в разделы СО (ИОС) | C30: ВОР 160 | D30: Поддон душевой стальной эмалированный мелкий, тип ПДСм-800 высотой 150 мм, пластмассовый унифицированный сифон, пластмассовый выпуск с диаметром выпускной решетки 70 мм, диаметр сливного отверстия 50 мм, диаметр сливной гофры 40/50 мм | E30: 03-01/07.21П-ИОС 2.1.ГЧ Спецификация (Файл: 03- 01_07.21П-ИОС.2.pdf стр.: 1 2 3 4 5 6) | F30: к-т | G30: =Спецификация!G387 -> 32 | H30: =Спецификация!H387 -> 0 | I30: =Спецификация!I387 -> 0 | J30: 387 | K30: =IF(H30=0,"НЕТ ЦЕНЫ","проценено") -> НЕТ ЦЕНЫ | L30: ВОР, нет в СО
A31: 20 | B31: Позиции из ВОРов, вставленные в разделы СО (ИОС) | C31: ВОР 162 | D31: Мойка стальная эмалированная, одна чаша, с креплениями, с пластмассовым бутылочным сифоном и выпуском, размеры 500x500x160 мм | E31: 03-01/07.21П-ИОС 2.1.ГЧ Спецификация (Файл: 03- 01_07.21П-ИОС.2.pdf стр.: 1 2 3 4 5 6) | F31: к-т | G31: =Спецификация!G388 -> 8 | H31: =Спецификация!H388 -> 0 | I31: =Спецификация!I388 -> 0 | J31: 388 | K31: =IF(H31=0,"НЕТ ЦЕНЫ","проценено") -> НЕТ ЦЕНЫ | L31: ВОР, нет в СО
A32: 21 | B32: Позиции из ВОРов, вставленные в разделы СО (ИОС) | C32: ВОР 164 | D32: Трубы полипропиленовые для систем водоотведения, диаметр 50 мм | E32: 03-01/07.21П-ИОС 2.1.ГЧ Спецификация (Файл: 03- 01 07.21П-ИОС.2.pdf стр.: 1 2 3 4 5 6) | F32: м | G32: =Спецификация!G389 -> 269.46 | H32: =Спецификация!H389 -> 0 | I32: =Спецификация!I389 -> 0 | J32: 389 | K32: =IF(H32=0,"НЕТ ЦЕНЫ","проценено") -> НЕТ ЦЕНЫ | L32: ВОР, нет в СО
A33: 22 | B33: Позиции из ВОРов, вставленные в разделы СО (ИОС) | C33: ВОР 166 | D33: Трубы полипропиленовые для систем водоотведения, диаметр 110 мм | E33: 03-01/07.21П-ИОС 2.1.ГЧ Спецификация (Файл: 03- 01 07.21П-ИОС.2.pdf стр.: 1 2 3 4 5 6) | F33: м | G33: =Спецификация!G390 -> 449.1 | H33: =Спецификация!H390 -> 0 | I33: =Спецификация!I390 -> 0 | J33: 390 | K33: =IF(H33=0,"НЕТ ЦЕНЫ","проценено") -> НЕТ ЦЕНЫ | L33: ВОР, нет в СО
A34: 23 | B34: Позиции из ВОРов, вставленные в разделы СО (ИОС) | C34: ВОР 168 | D34: Трубы ХПВХ, номинальное давление 1,0 МПа, диаметр 110 мм, толщина стенки 5,3 мм, 1000 мм | E34: 03-01/07.21П-ИОС 2.1.ГЧ Спецификация (Файл: 03- 01_07.21П-ИОС.2.pdf стр.: 1 2 3 4 5 6) | F34: шт. | G34: =Спецификация!G391 -> 98.14 | H34: =Спецификация!H391 -> 0 | I34: =Спецификация!I391 -> 0 | J34: 391 | K34: =IF(H34=0,"НЕТ ЦЕНЫ","проценено") -> НЕТ ЦЕНЫ | L34: ВОР, нет в СО
A35: 24 | B35: Позиции из ВОРов, вставленные в разделы СО (ИОС) | C35: ВОР 170 | D35: Муфты противопожарные для пластиковых труб: РТМК-110 | E35: 03-01/07.21П-ИОС 2.1.ГЧ Спецификация (Файл: 03- 01 07.21П-ИОС.2.pdf стр.: 1 2 3 4 5 6) | F35: шт. | G35: =Спецификация!G392 -> 20 | H35: =Спецификация!H392 -> 0 | I35: =Спецификация!I392 -> 0 | J35: 392 | K35: =IF(H35=0,"НЕТ ЦЕНЫ","проценено") -> НЕТ ЦЕНЫ | L35: ВОР, нет в СО
A36: 25 | B36: Позиции из ВОРов, вставленные в разделы СО (ИОС) | C36: ВОР 173 | D36: Отвод 87,5° полипропиленовый для систем водоотведения, диаметр 50 мм | E36: 03-01/07.21П-ИОС 2.1.ГЧ Спецификация (Файл: 03- 01 07.21П-ИОС.2.pdf стр.: 1 2 3 4 5 6) | F36: шт. | G36: =Спецификация!G393 -> 76 | H36: =Спецификация!H393 -> 0 | I36: =Спецификация!I393 -> 0 | J36: 393 | K36: =IF(H36=0,"НЕТ ЦЕНЫ","проценено") -> НЕТ ЦЕНЫ | L36: ВОР, нет в СО
A37: 26 | B37: Позиции из ВОРов, вставленные в разделы СО (ИОС) | C37: ВОР 174 | D37: Отвод 87,5° полипропиленовый для систем водоотведения, диаметр 110 мм | E37: 03-01/07.21П-ИОС 2.1.ГЧ Спецификация (Файл: 03- 01 07.21П-ИОС.2.pdf стр.: 1 2 3 4 5 6) | F37: шт. | G37: =Спецификация!G394 -> 117 | H37: =Спецификация!H394 -> 0 | I37: =Спецификация!I394 -> 0 | J37: 394 | K37: =IF(H37=0,"НЕТ ЦЕНЫ","проценено") -> НЕТ ЦЕНЫ | L37: ВОР, нет в СО
A38: 27 | B38: Позиции из ВОРов, вставленные в разделы СО (ИОС) | C38: ВОР 175 | D38: Тройник полипропиленовый для систем водоотведения, диаметр 50 мм | E38: 03-01/07.21П-ИОС 2.1.ГЧ Спецификация (Файл: 03- 01 07.21П-ИОС.2.pdf стр.: 1 2 3 4 5 6) | F38: шт. | G38: =Спецификация!G395 -> 49 | H38: =Спецификация!H395 -> 0 | I38: =Спецификация!I395 -> 0 | J38: 395 | K38: =IF(H38=0,"НЕТ ЦЕНЫ","проценено") -> НЕТ ЦЕНЫ | L38: ВОР, нет в СО
... A51: 40 | B51: Позиции из ВОРов, вставленные в разделы СО (ИОС) | C51: ВОР 202 | D51: Тройник полипропиленовый для систем водоотведения, диаметр 110 мм | E51: 03-01/07.21П-ИОС 2.1.ГЧ Спецификация (Файл: 03- 01_07.21П-ИОС.2.pdf стр.: 1 2 3 4 5 6) | F51: шт. | G51: =Спецификация!G408 -> 21 | H51: =Спецификация!H408 -> 0 | I51: =Спецификация!I408 -> 0 | J51: 408 | K51: =IF(H51=0,"НЕТ ЦЕНЫ","проценено") -> НЕТ ЦЕНЫ | L51: ВОР, нет в СО
A52: 41 | B52: Позиции из ВОРов, вставленные в разделы СО (ИОС) | C52: ВОР 74 | D52: Муфта полиэтиленовая соединительная для дренажных труб, диаметр 160 мм | E52: 03-01/07.21П-ИОС 3.1 ГЧ. Спецификация л. 1 (Файл: 03-01_07.21П-ИОС3.1.pdf, стр.: 1) | F52: шт. | G52: =Спецификация!G423 -> 35 | H52: =Спецификация!H423 -> 0 | I52: =Спецификация!I423 -> 0 | J52: 423 | K52: =IF(H52=0,"НЕТ ЦЕНЫ","проценено") -> НЕТ ЦЕНЫ | L52: ВОР, нет в СО
A53: 42 | B53: Позиции из ВОРов, вставленные в разделы СО (ИОС) | C53: ВОР 85 | D53: Люк чугунный с решеткой для дождеприемного колодца, номинальная нагрузка 15 кН, диаметр лаза 600 мм | E53: 03-01/07.21П-ИОС 3.1 ГЧ. Спецификация л. 1 (Файл: 03-01_07.21П-ИОС3.1.pdf, стр.: 1) | F53: шт. | G53: =Спецификация!G424 -> 22 | H53: =Спецификация!H424 -> 0 | I53: =Спецификация!I424 -> 0 | J53: 424 | K53: =IF(H53=0,"НЕТ ЦЕНЫ","проценено") -> НЕТ ЦЕНЫ | L53: ВОР, нет в СО
A54: 43 | B54: Позиции из ВОРов, вставленные в разделы СО (ИОС) | C54: ВОР 87 | D54: Трубы дренажные гофрированные двухслойные полипропиленовые, SN16, диаметр 200 мм | E54: 03-01/07.21П-ИОС 3.1 ГЧ. Спецификация л. 2 (Файл: 03-01_07.21П-ИОС3.1.pdf, стр.: 1) | F54: м | G54: =Спецификация!G425 -> 25.25 | H54: =Спецификация!H425 -> 0 | I54: =Спецификация!I425 -> 0 | J54: 425 | K54: =IF(H54=0,"НЕТ ЦЕНЫ","проценено") -> НЕТ ЦЕНЫ | L54: ВОР, нет в СО
A55: 44 | B55: Позиции из ВОРов, вставленные в разделы СО (ИОС) | C55: ВОР 89 | D55: Трубы дренажные гофрированные двухслойные полипропиленовые, SN16, диаметр 250 мм | E55: 03-01/07.21П-ИОС 3.1 ГЧ. Спецификация л. 2 (Файл: 03-01_07.21П-ИОС3.1.pdf, стр.: 1) | F55: м | G55: =Спецификация!G426 -> 363.6 | H55: =Спецификация!H426 -> 0 | I55: =Спецификация!I426 -> 0 | J55: 426 | K55: =IF(H55=0,"НЕТ ЦЕНЫ","проценено") -> НЕТ ЦЕНЫ | L55: ВОР, нет в СО
A56: 45 | B56: Позиции из ВОРов, вставленные в разделы СО (ИОС) | C56: ВОР 91 | D56: Трубы дренажные гофрированные двухслойные полипропиленовые, SN16, диаметр 315 мм | E56: 03-01/07.21П-ИОС 3.1 ГЧ. Спецификация л. 2 (Файл: 03-01_07.21П-ИОС3.1.pdf, стр.: 1) | F56: м | G56: =Спецификация!G427 -> 303 | H56: =Спецификация!H427 -> 0 | I56: =Спецификация!I427 -> 0 | J56: 427 | K56: =IF(H56=0,"НЕТ ЦЕНЫ","проценено") -> НЕТ ЦЕНЫ | L56: ВОР, нет в СО
A57: 46 | B57: Позиции из ВОРов, вставленные в разделы СО (ИОС) | C57: ВОР 92 | D57: Муфта полиэтиленовая соединительная для дренажных труб, диаметр 200 мм | E57: 03-01/07.21П-ИОС 3.1 ГЧ. Спецификация л. 2 (Файл: 03-01 07.21П-ИОС3.1.pdf, стр.: 1) | F57: шт. | G57: =Спецификация!G428 -> 8 | H57: =Спецификация!H428 -> 0 | I57: =Спецификация!I428 -> 0 | J57: 428 | K57: =IF(H57=0,"НЕТ ЦЕНЫ","проценено") -> НЕТ ЦЕНЫ | L57: ВОР, нет в СО
A58: 47 | B58: Позиции из ВОРов, вставленные в разделы СО (ИОС) | C58: ВОР 93 | D58: Муфта полиэтиленовая электросварная, ПЭ100, SDR11, диаметр 250 мм | E58: 03-01/07.21П-ИОС 3.1 ГЧ. Спецификация л. 2 (Файл: 03-01 07.21П-ИОС3.1.pdf, стр.: 1) | F58: шт. | G58: =Спецификация!G429 -> 36 | H58: =Спецификация!H429 -> 0 | I58: =Спецификация!I429 -> 0 | J58: 429 | K58: =IF(H58=0,"НЕТ ЦЕНЫ","проценено") -> НЕТ ЦЕНЫ | L58: ВОР, нет в СО
A59: 48 | B59: Позиции из ВОРов, вставленные в разделы СО (ИОС) | C59: ВОР 94 | D59: Муфта полиэтиленовая электросварная, ПЭ100, SDR11, диаметр 315 мм | E59: 03-01/07.21П-ИОС 3.1 ГЧ. Спецификация л. 2 (Файл: 03-01 07.21П-ИОС3.1.pdf, стр.: 1) | F59: шт. | G59: =Спецификация!G430 -> 18 | H59: =Спецификация!H430 -> 0 | I59: =Спецификация!I430 -> 0 | J59: 430 | K59: =IF(H59=0,"НЕТ ЦЕНЫ","проценено") -> НЕТ ЦЕНЫ | L59: ВОР, нет в СО
A60: 49 | B60: Позиции из ВОРов, вставленные в разделы СО (ИОС) | C60: ВОР 102 | D60: Люк чугунный с решеткой для дождеприемного колодца, номинальная нагрузка 15 кН, диаметр лаза 600 мм | E60: 03-01/07.21П-ИОС 3.1 ГЧ. Спецификация л. 2 (Файл: 03-01_07.21П-ИОС3.1.pdf, стр.: 1) | F60: шт. | G60: =Спецификация!G431 -> 29 | H60: =Спецификация!H431 -> 0 | I60: =Спецификация!I431 -> 0 | J60: 431 | K60: =IF(H60=0,"НЕТ ЦЕНЫ","проценено") -> НЕТ ЦЕНЫ | L60: ВОР, нет в СО
A61: 50 | B61: Позиции из ВОРов, вставленные в разделы СО (ИОС) | C61: ВОР 2 | D61: Трубы дренажные гофрированные двухслойные полипропиленовые, SN16, диаметр 200 мм | E61: 03-01/07.21П-ИОС3.2.СО л.1 (Файл: 03-01_07.21П- ИОС3.2.pdf, стр.: 17) | F61: м | G61: =Спецификация!G439 -> 385.67675 | H61: =Спецификация!H439 -> 0 | I61: =Спецификация!I439 -> 0 | J61: 439 | K61: =IF(H61=0,"НЕТ ЦЕНЫ","проценено") -> НЕТ ЦЕНЫ | L61: ВОР, нет в СО
A62: 51 | B62: Позиции из ВОРов, вставленные в разделы СО (ИОС) | C62: ВОР 95 | D62: Элеватор водоструйный стальной, фланцевый, для систем отопления, давление 1,6 МПа, 40с 10б, № 2 | E62: 03-01/07.21П-ИОС.4.1.СО л.5 (Файл: 03-0107.21П- ИОС 4.3.pdf, стр.: 1 2 3 4 5 6) | F62: шт. | G62: =Спецификация!G558 -> 3 | H62: =Спецификация!H558 -> 0 | I62: =Спецификация!I558 -> 0 | J62: 558 | K62: =IF(H62=0,"НЕТ ЦЕНЫ","проценено") -> НЕТ ЦЕНЫ | L62: ВОР, нет в СО
A63: 52 | B63: Позиции из ВОРов, вставленные в разделы СО (ИОС) | C63: ВОР 352 | D63: Крепления (хомуты) для воздуховодов СТД 205 | E63: 03-01/07.21П-ИОС.4.2.СО Спецификация л.20 (Файл: 03-01_07.21П-ИОС.4.2.pdf, стр.: 1 2 3 4 5) | F63: т | G63: =Спецификация!G1226 -> 4.0948 | H63: =Спецификация!H1226 -> 0 | I63: =Спецификация!I1226 -> 0 | J63: 1226 | K63: =IF(H63=0,"НЕТ ЦЕНЫ","проценено") -> НЕТ ЦЕНЫ | L63: ВОР, нет в СО
A64: 53 | B64: Позиции из ВОРов, вставленные в разделы СО (ИОС) | C64: ВОР 398 | D64: Крепления (хомуты) для воздуховодов СТД 205 | E64: 03-01/07.21П-ИОС.4.2.СО Спецификация л.22 (Файл: 03-01_07.21П-ИОС.4.2.pdf, стр.: 1 2 3 4 5) | F64: т | G64: =Спецификация!G1227 -> 0.4601 | H64: =Спецификация!H1227 -> 0 | I64: =Спецификация!I1227 -> 0 | J64: 1227 | K64: =IF(H64=0,"НЕТ ЦЕНЫ","проценено") -> НЕТ ЦЕНЫ | L64: ВОР, нет в СО
A65: 54 | B65: Позиции из ВОРов, вставленные в разделы СО (ИОС) | C65: ВОР 470 | D65: Комплект медных рефнет (разветвителей) с переходниками для газовой и жидкостной линий трубных систем кондиционирования, диаметр входа рефнеты газовой линии 12,7x15,88x19,05 мм, диаметр входа рефнеты жидкостной линии 9,52x12,7 мм | E65: 03-01/07.21П-ИОС.4.2.СО Спецификация л.24 (Файл: 03-01_07.21П-ИОС.4.2.pdf, стр.: 1 2 3 4 5) | F65: к-т | G65: =Спецификация!G1228 -> 18 | H65: =Спецификация!H1228 -> 0 | I65: =Спецификация!I1228 -> 0 | J65: 1228 | K65: =IF(H65=0,"НЕТ ЦЕНЫ","проценено") -> НЕТ ЦЕНЫ | L65: ВОР, нет в СО
A66: 55 | B66: Позиции из ВОРов, вставленные в разделы СО (ИОС) | C66: ВОР 471 | D66: Комплект медных рефнет (разветвителей) с переходниками для газовой и жидкостной линий трубных систем кондиционирования, диаметр входа рефнеты газовой линии 12,7x15,88x19,05 мм, диаметр входа рефнеты жидкостной линии 9,52x12,7 мм | E66: 03-01/07.21П-ИОС.4.2.СО Спецификация л.24 (Файл: 03-01_07.21П-ИОС.4.2.pdf, стр.: 1 2 3 4 5) | F66: к-т | G66: =Спецификация!G1229 -> 9 | H66: =Спецификация!H1229 -> 0 | I66: =Спецификация!I1229 -> 0 | J66: 1229 | K66: =IF(H66=0,"НЕТ ЦЕНЫ","проценено") -> НЕТ ЦЕНЫ | L66: ВОР, нет в СО
A67: 56 | B67: Позиции из ВОРов, вставленные в разделы СО (ИОС) | C67: ВОР 472 | D67: Комплект медных рефнет (разветвителей) с переходниками для газовой и жидкостной линий трубных систем кондиционирования, диаметр входа рефнеты газовой линии 12,7x15,88x19,05 мм, диаметр входа рефнеты жидкостной линии 9,52x12,7 мм | E67: 03-01/07.21П-ИОС.4.2.СО Спецификация л.24 (Файл: 03-01_07.21П-ИОС.4.2.pdf, стр.: 1 2 3 4 5) | F67: к-т | G67: =Спецификация!G1230 -> 9 | H67: =Спецификация!H1230 -> 0 | I67: =Спецификация!I1230 -> 0 | J67: 1230 | K67: =IF(H67=0,"НЕТ ЦЕНЫ","проценено") -> НЕТ ЦЕНЫ | L67: ВОР, нет в СО
A68: 57 | B68: Позиции из ВОРов, вставленные в разделы СО (ИОС) | C68: ВОР 482 | D68: Насос поверхностный ручной, производительность 1,32 м3/ч, максимальная высота всасывания 6 м | E68: 03-01/07.21П-ИОС.4.2.СО Спецификация л.24 (Файл: 03-01_07.21П-ИОС.4.2.pdf, стр.: 1 2 3 4 5) | F68: шт | G68: =Спецификация!G1231 -> 2 | H68: =Спецификация!H1231 -> 0 | I68: =Спецификация!I1231 -> 0 | J68: 1231 | K68: =IF(H68=0,"НЕТ ЦЕНЫ","проценено") -> НЕТ ЦЕНЫ | L68: ВОР, нет в СО. Проверить: насос ручной опрессовочный - инструмент для испытаний, решить, включать ли в закупку
A69: 58 | B69: Позиции из ВОРов, вставленные в разделы СО (ИОС) | C69: ВОР 34 | D69: Отвод 90° сегментный стальной оцинкованный | E69: 03-01/07.21П-ИОС.4.4.СО л. 4 (Файл: 03-01_07.21П- HCOM.pdf, стр.: 2) | F69: шт | G69: =Спецификация!G1514 -> 8 | H69: =Спецификация!H1514 -> 0 | I69: =Спецификация!I1514 -> 0 | J69: 1514 | K69: =IF(H69=0,"НЕТ ЦЕНЫ","проценено") -> НЕТ ЦЕНЫ | L69: ВОР, нет в СО. Проверить по ИОС.4.4 л.4: кожух изоляции отвода (в СО нет) или стальной отвод (в СО есть 90-159х5 и 90-42,4х5 по 4 шт = те же 4+4)?
A70: 59 | B70: Позиции из ВОРов, вставленные в разделы СО (ИОС) | C70: ВОР 74 | D70: Отвод 90° сегментный стальной оцинкованный | E70: 03-01/07.21П-ИОС.4.4.СО л. 4,5 (Файл: 03- 01 07.21П-ИОС4.4.pdf, стр.: 4 5) | F70: шт | G70: =Спецификация!G1515 -> 8 | H70: =Спецификация!H1515 -> 0 | I70: =Спецификация!I1515 -> 0 | J70: 1515 | K70: =IF(H70=0,"НЕТ ЦЕНЫ","проценено") -> НЕТ ЦЕНЫ | L70: ВОР, нет в СО. Проверить по ИОС.4.4 л.4,5: кожух изоляции отвода (в СО нет) или стальной отвод (в СО есть 90-159х5 и 90-42,4х5 по 4 шт = те же 4+4)?
A71: 60 | B71: Позиции из ВОРов, вставленные в разделы СО (ИОС) | C71: ВОР 77 | D71: Заглушка стальная фланцевая, номинальный диаметр 100 мм | E71: 03-01/07.21П-ИОС.4.4.СО л. 4,5 (Файл: 03- 01 07.21П-ИОС4.4.pdf, стр.: 4 5) | F71: шт | G71: =Спецификация!G1516 -> 2 | H71: =Спецификация!H1516 -> 0 | I71: =Спецификация!I1516 -> 0 | J71: 1516 | K71: =IF(H71=0,"НЕТ ЦЕНЫ","проценено") -> НЕТ ЦЕНЫ | L71: ВОР, нет в СО. Проверить: в СО есть заглушка фланцевая Ду80 Ру40, 2 шт — у ВОРа Ду100. Расхождение диаметра
A72: 61 | B72: Позиции из ВОРов, вставленные в разделы СО (ИОС) | C72: ВОР 100 | D72: Кабель оптический ИКБ-Т-А12-6.0 | E72: 03-01/07.21П-ИОС.5.1.СО л.6 (Файл: Том СС 03- 0107.21П-ИОС.5.1.pdf, стр.: 1 2 3 4) | F72: м | G72: =Спецификация!G1894 -> 160 | H72: =Спецификация!H1894 -> 0 | I72: =Спецификация!I1894 -> 0 | J72: 1894 | K72: =IF(H72=0,"НЕТ ЦЕНЫ","проценено") -> НЕТ ЦЕНЫ | L72: ВОР, нет в СО — ПРОВЕРИТЬ: та же длина 160 м, что у поз. 1.121 (ВОК 8 волокон), марка иная
D73: Итого по разделу | I73: =SUM(I27:I72) -> 476400
A75: ВОР 01-01-01 — Общестроительные работы и конструкции (КР) (19 поз.)
A76: 62 | B76: ВОР 01-01-01 — Общестроительные работы и конструкции (КР) | C76: ВОР 7 | D76: Песок природный для строительных работ I класс, средний | E76: 03-01/07.21П-ПОС.ТЧ. Приложение Д л. 179 (Файл: 03-01 07.21П-КР.pdf, стр.: 179) | F76: м3 | G76: =Спецификация!G4096 -> 15581.053 | H76: =Спецификация!H4096 -> 1600 | I76: =Спецификация!I4096 -> 24929684 | J76: 4096 | K76: =IF(H76=0,"НЕТ ЦЕНЫ","проценено") -> проценено | L76: ВОР 01-01-01, нет в СО; есть в КР.СО
A77: 63 | B77: ВОР 01-01-01 — Общестроительные работы и конструкции (КР) | C77: ВОР 10 | D77: Щебень из плотных горных пород для строительных работ М 800, фракция 5(3)-10 мм | E77: 03-01/07.21П-КР.СО. Спецификация п. 34 (Файл: 03- 01_07.21П-КР.pdf, стр.: 4) | F77: м3 | G77: =Спецификация!G4097 -> 40.8789 | H77: =Спецификация!H4097 -> 4000 | I77: =Спецификация!I4097 -> 163515.6 | J77: 4097 | K77: =IF(H77=0,"НЕТ ЦЕНЫ","проценено") -> проценено | L77: ВОР 01-01-01, нет в СО — в ВОРе: 0.483×3 + 1.288×2 + 0.575×2 + 0.31×2 + 0.38×2 + 0.69×2 + 3.68 + 10.626 + 1.38 + 1.1 + 1.208 + 0.356 + 2.254 + 0.966 + 0.713 + 1.046 + 3.864 + 0.805 + 0.92 + 4.025 = 40.879; есть в КР.СО
A78: 64 | B78: ВОР 01-01-01 — Общестроительные работы и конструкции (КР) | C78: ВОР 11 | D78: Щебень из плотных горных пород для строительных работ М 800, фракция 20-40 мм | E78: 03-01/07.21П-КР.СО. Спецификация п. 31 (Файл: 03- 01_07.21П-КР.pdf, стр.: 4) | F78: м3 | G78: =Спецификация!G4098 -> 1016.8785 | H78: =Спецификация!H4098 -> 4000 | I78: =Спецификация!I4098 -> 4067514 | J78: 4098 | K78: =IF(H78=0,"НЕТ ЦЕНЫ","проценено") -> проценено | L78: ВОР 01-01-01, нет в СО — в ВОРе: 12.316×3 + 32.844×2 + 9.752×2 + 17.595×2 + 93.84 + 270.963 + 35.54 + 29.256 + 30.774 + 9.143 + 14.777 + 57.477 + 24.633 + 18.067 + 7.82 + 26.599 + 14.775 + 98.532 + 20.516 + 7.935 + 24.38 + 74.52 = 1016.879; есть в КР.СО
A79: 65 | B79: ВОР 01-01-01 — Общестроительные работы и конструкции (КР) | C79: ВОР 13 | D79: Смеси бетонные мелкозернистого бетона (БСМ), класс В10 (М150) | E79: 03-01/07.21П-КР.СО. Спецификация п. 20 (Файл: 03- 01_07.21П-КР.pdf, стр.: 3) | F79: м3 | G79: =Спецификация!G4099 -> 889.236 | H79: =Спецификация!H4099 -> 8500 | I79: =Спецификация!I4099 -> 7558506 | J79: 4099 | K79: =IF(H79=0,"НЕТ ЦЕНЫ","проценено") -> проценено | L79: ВОР 01-01-01, нет в СО — в ВОРе: 3.06×3 + 24.48×2 + 9.792×2 + 3.672×2 + 6.12×2 + 1.938×2 + 2.448×2 + 4.59×2 + 67.32 + 9.18 + 7.344 + 7.65 + 2.244 + 14.28 + 4.488 + 6.63 + 5.1 + 418.2 + 188.7 + 16.32 + 11.22 + 15.3 = 889.236; есть в КР.СО
A80: 66 | B80: ВОР 01-01-01 — Общестроительные работы и конструкции (КР) | C80: ВОР 15 | D80: Доска обрезная антисептированная, естественной влажности, длина 4-6 м, ширина 150 мм, толщина 40 мм, сорт II | E80: 03-01/07.21П-КР.СО. Спецификация п. 21 (Файл: 03- 01_07.21П-КР.pdf, стр.: 3) | F80: м3 | G80: =Спецификация!G4100 -> 28.3894 | H80: =Спецификация!H4100 -> 25000 | I80: =Спецификация!I4100 -> 709735 | J80: 4100 | K80: =IF(H80=0,"НЕТ ЦЕНЫ","проценено") -> проценено | L80: ВОР 01-01-01, нет в СО — в ВОРе: 0.424×3 + 0.132×3 + 0.363×2 + 0.369×2 + 0.264×2 + 0.424×2 + 0.13×2 + 1.84 + 3.8 + 0.133 + 0.566 + 0.577 + 0.107 + 0.218 + 1.697 + 0.289 + 0.26 + 6.912 + 2.478 + 1.39 + 1.115 + 0.095 + 0.371 + 0.932 + 0.312 + 0.014 + 0.217 + 0.094 + 0.204 = 28.389; есть в КР.СО
A81: 67 | B81: ВОР 01-01-01 — Общестроительные работы и конструкции (КР) | C81: ВОР 16 | D81: Смеси бетонные тяжелого бетона (БСТ) на гранитном щебне, класс В25, F(1)200, W6 | E81: 03-01/07.21П-КР.СО. Спецификация п. 21 (Файл: 03- 01_07.21П-КР.pdf, стр.: 3) | F81: м3 | G81: =Спецификация!G4101 -> 3946.1733 | H81: =Спецификация!H4101 -> 8500 | I81: =Спецификация!I4101 -> 33542473 | J81: 4101 | K81: =IF(H81=0,"НЕТ ЦЕНЫ","проценено") -> проценено | L81: ВОР 01-01-01, нет в СО — в ВОРе: 1.53×5 + 9.744×5 + 4.6×3 + 2.305×3 + 39.382×2 + 6.12×2 + 17.722×2 + 2.764×2 + 3.366×2 + 23.751×2 + 126.672 + 24.48 + 324.901 + 50.49 + 35.525 + 15.3 + 29.232 + 12.24 + 30.755 + 4.59 + 9.135 + 68.918 + 10.72 + 29.537 + 21.66 + 7.816 + 31.901 + 4.967 + 118.146 + 18.401 + 20.503 + 3.06 + 7.917 + 24.36 + 154.787 + 55.013 + 982.52 + 785.61 + 66.99 + 28 + 150 + 70.035 + 6.5 + 53 + 65.975 + 54.81 + 95.41 + 83 = 3946.173; есть в КР.СО
A82: 68 | B82: ВОР 01-01-01 — Общестроительные работы и конструкции (КР) | C82: ВОР 17 | D82: Прокат арматурный для железобетонных конструкций, класс A500C, диаметр 16 мм | E82: 03-01/07.21П-КР.СО. Спецификация п. 22 (Файл: 03- 01_07.21П-КР.pdf, стр.: 3) | F82: т | G82: =Спецификация!G4102 -> 259.6858 | H82: =Спецификация!H4102 -> 110000 | I82: =Спецификация!I4102 -> 28565438 | J82: 4102 | K82: =IF(H82=0,"НЕТ ЦЕНЫ","проценено") -> проценено | L82: ВОР 01-01-01, нет в СО — в ВОРе: 0.093×5 + 0.155×3 + 0.051×3 + 0.52×2 + 0.206×2 + 0.113×2 + 0.8 + 1.7 + 0.412 + 0.154 + 0.11 + 0.361 + 0.167 + 0.618 + 0.103 + 169.3 + 69.4 + 6.1 + 7.7 = 259.686; есть в КР.СО
A83: 69 | B83: ВОР 01-01-01 — Общестроительные работы и конструкции (КР) | C83: ВОР 18 | D83: Прокат арматурный для железобетонных конструкций, класс A500C, диаметр 12 мм | E83: 03-01/07.21П-КР.СО. Спецификация п. 23 (Файл: 03- 01_07.21П-КР.pdf, стр.: 3) | F83: т | G83: =Спецификация!G4103 -> 240.6663 | H83: =Спецификация!H4103 -> 110000 | I83: =Спецификация!I4103 -> 26473293 | J83: 4103 | K83: =IF(H83=0,"НЕТ ЦЕНЫ","проценено") -> проценено | L83: ВОР 01-01-01, нет в СО — в ВОРе: 0.64×5 + 1.422×2 + 0.422×2 + 0.836×2 + 4.5 + 11.74 + 1.54 + 1.267 + 1.333 + 0.396 + 2.489 + 1.067 + 0.782 + 0.339 + 1.152 + 4.267 + 0.889 + 0.343 + 1.056 + 6.044 + 2.534 + 101.5 + 10.4 + 3.1 + 28.436 + 12.639 + 4.9 + 0.57 + 4.211 + 2 + 9.3 + 6.1 + 7.211 = 240.666; есть в КР.СО
A84: 70 | B84: ВОР 01-01-01 — Общестроительные работы и конструкции (КР) | C84: ВОР 19 | D84: Сталь арматурная горячекатаная гладкая, класс A-I, диаметр 6-22 мм | E84: 03-01/07.21П-КР.СО. Спецификация п. 24,25 (Файл: 03-01_07.21П-КР.pdf, стр.: 3) | F84: т | G84: =Спецификация!G4104 -> 41.4011 | H84: =Спецификация!H4104 -> 110000 | I84: =Спецификация!I4104 -> 4554121 | J84: 4104 | K84: =IF(H84=0,"НЕТ ЦЕНЫ","проценено") -> проценено | L84: ВОР 01-01-01, нет в СО — в ВОРе: 0.229×5 + 0.382×4 + 0.127×3 + 1.272×2 + 0.509×2 + 0.28×2 + 2.04 + 4.2 + 1.018 + 0.24 + 0.89 + 0.412 + 1.526 + 0.254 + 6.316 + 2.648 + 4.5 + 2.2 + 1.89 + 1.472 + 0.614 + 1.3 + 0.037 + 0.269 + 0.9 + 1.5 = 41.401; есть в КР.СО
A85: 71 | B85: ВОР 01-01-01 — Общестроительные работы и конструкции (КР) | C85: ВОР 21 | D85: Болты анкерные фундаментные стальные в комплекте с двумя гайками М36 и шайбами М36, тип 1, диаметр М36 | E85: 03-01/07.21П-КР.СО. Спецификация п. 26 (Файл: 03- 01_07.21П-КР.pdf, стр.: 3) | F85: т | G85: =Спецификация!G4105 -> 10.4733 | H85: =Спецификация!H4105 -> 140000 | I85: =Спецификация!I4105 -> 1466262 | J85: 4105 | K85: =IF(H85=0,"НЕТ ЦЕНЫ","проценено") -> проценено | L85: ВОР 01-01-01, нет в СО — в ВОРе: 0.19×7 + 0.095×3 + 1.52 + 3.136 + 0.57 + 0.095 + 0.38 + 0.19 + 0.019 + 0.665 + 0.285 + 0.475 + 1.14 + 0.38 = 10.473; есть в КР.СО
A86: 72 | B86: ВОР 01-01-01 — Общестроительные работы и конструкции (КР) | C86: ВОР 23 | D86: Мастика битумно-резиновая изоляционная МБР-100 | E86: 03-01/07.21П-КР.СО. Спецификация п. 27 (Файл: 03- 01_07.21П-КР.pdf, стр.: 3) | F86: т | G86: =Спецификация!G4106 -> 55.4579 | H86: =Спецификация!H4106 -> 282000 | I86: =Спецификация!I4106 -> 15639128 | J86: 4106 | K86: =IF(H86=0,"НЕТ ЦЕНЫ","проценено") -> проценено | L86: ВОР 01-01-01, нет в СО — в ВОРе: 0.205×3 + 0.547×2 + 0.246×2 + 0.162×2 + 0.292×2 + 1.555 + 4.514 + 0.593 + 0.488 + 0.513 + 0.152 + 0.958 + 0.41 + 0.301 + 0.13 + 0.443 + 1.642 + 0.342 + 0.132 + 0.406 + 2.772 + 1.231 + 18.06 + 3.3 + 9.366 + 1.176 + 1.013 + 1.281 + 1.57 = 55.458; есть в КР.СО
A87: 73 | B87: ВОР 01-01-01 — Общестроительные работы и конструкции (КР) | C87: ВОР 24 | D87: Битум нефтяной строительный БН-90/10 | E87: 03-01/07.21П-КР.СО. Спецификация п. 27 (Файл: 03- 01_07.21П-КР.pdf, стр.: 3) | F87: т | G87: =Спецификация!G4107 -> 2.7434 | H87: =Спецификация!H4107 -> 48000 | I87: =Спецификация!I4107 -> 131683.2 | J87: 4107 | K87: =IF(H87=0,"НЕТ ЦЕНЫ","проценено") -> проценено | L87: ВОР 01-01-01, нет в СО — в ВОРе: 0.014×3 + 0.036×2 + 0.016×2 + 0.011×2 + 0.019×2 + 0.104 + 0.301 + 0.04 + 0.033 + 0.034 + 0.01 + 0.064 + 0.027 + 0.02 + 0.009 + 0.03 + 0.109 + 0.023 + 0.009 + 0.027 + 0.185 + 0.082 + 0.688 + 0.12 + 0.357 + 0.045 + 0.068 + 0.049 + 0.105 = 2.743; есть в КР.СО
... A94: 80 | B94: ВОР 01-01-01 — Общестроительные работы и конструкции (КР) | C94: ВОР 552 | D94: Прокат арматурный для железобетонных конструкций, класс A500C, диаметр 10 мм | E94: 03-01/07.21П-КР.СО. Спецификация п. 456-459 (Файл: 03-01_07.21П-КР.pdf, стр.: 21) | F94: т | G94: =Спецификация!G4114 -> 34.937 | H94: =Спецификация!H4114 -> 110000 | I94: =Спецификация!I4114 -> 3843070 | J94: 4114 | K94: =IF(H94=0,"НЕТ ЦЕНЫ","проценено") -> проценено | L94: ВОР 01-01-01, нет в СО — в ВОРе: 13.856+6.645+0.346+2.845+4.4+6.845 = 34.937; есть в КР.СО
D95: Итого по разделу | I95: =SUM(I76:I94) -> 1.9062115e+08
A97: ВОР 02-01-02 — Металлоконструкции (9 поз.)
A98: 81 | B98: ВОР 02-01-02 — Металлоконструкции | C98: ВОР 1 | D98: Колонны со связями | E98: 03-01/07.21П-КР.СО л. 1 п.2 (Файл: Раздел_03- 0107.21П-КР!.pdf, стр.: 1) | F98: т | G98: =Спецификация!G4116 -> 555.91 | H98: =Спецификация!H4116 -> 0 | I98: =Спецификация!I4116 -> 0 | J98: 4116 | K98: =IF(H98=0,"НЕТ ЦЕНЫ","проценено") -> НЕТ ЦЕНЫ | L98: ВОР 02-01-02, нет в СО — в ВОРе: 473.37+82.54 = 555.91
A99: 82 | B99: ВОР 02-01-02 — Металлоконструкции | C99: ВОР 2 | D99: Прокатные двутавры из стали С245-4 | E99: 03-01/07.21П-КР.СО л. 1 п.2 (Файл: Раздел_03- 0107.21П-КР!.pdf, стр.: 1) | F99: т | G99: =Спецификация!G4117 -> 409.06 | H99: =Спецификация!H4117 -> 210000 | I99: =Спецификация!I4117 -> 85902600 | J99: 4117 | K99: =IF(H99=0,"НЕТ ЦЕНЫ","проценено") -> проценено | L99: ВОР 02-01-02, нет в СО
A100: 83 | B100: ВОР 02-01-02 — Металлоконструкции | C100: ВОР 3 | D100: Сталь листовая С245-4 | E100: 03-01/07.21П-КР.СО л. 1 п.2 (Файл: Раздел_03- 0107.21П-КР!.pdf, стр.: 1) | F100: т | G100: =Спецификация!G4118 -> 164.194 | H100: =Спецификация!H4118 -> 210000 | I100: =Спецификация!I4118 -> 34480740 | J100: 4118 | K100: =IF(H100=0,"НЕТ ЦЕНЫ","проценено") -> проценено | L100: ВОР 02-01-02, нет в СО — в ВОРе: 64.31+77.25+8.29+13.48+0.864 = 164.194
A101: 84 | B101: ВОР 02-01-02 — Металлоконструкции | C101: ВОР 5 | D101: Прокатные двутавры из стали С345-5 | E101: 03-01/07.21П-КР.СО л. 1 п.2 (Файл: Раздел_03- 0107.21П-КР!.pdf, стр.: 1) | F101: т | G101: =Спецификация!G4119 -> 262.32 | H101: =Спецификация!H4119 -> 210000 | I101: =Спецификация!I4119 -> 55087200 | J101: 4119 | K101: =IF(H101=0,"НЕТ ЦЕНЫ","проценено") -> проценено | L101: ВОР 02-01-02, нет в СО — в ВОРе: 48.29+141.22+72.81 = 262.32
A102: 85 | B102: ВОР 02-01-02 — Металлоконструкции | C102: ВОР 6 | D102: Сталь листовая С355-5 | E102: 03-01/07.21П-КР.СО л. 1 п.2 (Файл: Раздел_03- 0107.21П-КР!.pdf, стр.: 1) | F102: т | G102: =Спецификация!G4120 -> 319.5 | H102: =Спецификация!H4120 -> 210000 | I102: =Спецификация!I4120 -> 67095000 | J102: 4120 | K102: =IF(H102=0,"НЕТ ЦЕНЫ","проценено") -> проценено | L102: ВОР 02-01-02, нет в СО — в ВОРе: 34.25+84.48+200.77 = 319.5
A103: 86 | B103: ВОР 02-01-02 — Металлоконструкции | C103: ВОР 8 | D103: Гнутосварные профили из стали С245-4 | E103: 03-01/07.21П-КР.СО л. 2 п.4 (Файл: Раздел_03- 0107.21П-КР!.pdf, стр.: 2) | F103: т | G103: =Спецификация!G4121 -> 182.53 | H103: =Спецификация!H4121 -> 210000 | I103: =Спецификация!I4121 -> 38331300 | J103: 4121 | K103: =IF(H103=0,"НЕТ ЦЕНЫ","проценено") -> проценено | L103: ВОР 02-01-02, нет в СО — в ВОРе: 22.11+38.74+121.68 = 182.53
A104: 87 | B104: ВОР 02-01-02 — Металлоконструкции | C104: ВОР 13 | D104: Металлоконструкции вспомогательного назначения с преобладанием толстолистовой стали или профильного проката, с отверстиями и без, сталь С245-4 | E104: 03-01/07.21П-КР.СО л. 1 п.1 (Файл: Раздел_03- 0107.21П-КР!.pdf, стр.: 1) | F104: т | G104: =Спецификация!G4122 -> 527.28 | H104: =Спецификация!H4122 -> 210000 | I104: =Спецификация!I4122 -> 110728800 | J104: 4122 | K104: =IF(H104=0,"НЕТ ЦЕНЫ","проценено") -> проценено | L104: ВОР 02-01-02, нет в СО
A105: 88 | B105: ВОР 02-01-02 — Металлоконструкции | C105: ВОР 25 | D105: Швеллеры горячекатаные из стали С245-4 | E105: 03-01/07.21П-КР.СО л. 2 п.6 (Файл: Раздел_03- 0107.21П-КР!.pdf, стр.: 2) | F105: т | G105: =Спецификация!G4123 -> 6.48 | H105: =Спецификация!H4123 -> 210000 | I105: =Спецификация!I4123 -> 1360800 | J105: 4123 | K105: =IF(H105=0,"НЕТ ЦЕНЫ","проценено") -> проценено | L105: ВОР 02-01-02, нет в СО
A106: 89 | B106: ВОР 02-01-02 — Металлоконструкции | C106: ВОР 29 | D106: Краска огнезащитная из термостойких, газообразующих и пенообразующих наполнителей | E106: 03-01/07.21П-КР.СО л. 3. п 15 (Файл: Раздел_03- 0107.21П-КР!.pdf, стр.: 3) | F106: кг | G106: =Спецификация!G4124 -> 59732.01 | H106: =Спецификация!H4124 -> 1100 | I106: =Спецификация!I4124 -> 65705211 | J106: 4124 | K106: =IF(H106=0,"НЕТ ЦЕНЫ","проценено") -> проценено | L106: ВОР 02-01-02, нет в СО — в ВОРе: 30984.525+369.6+-107.52+10699.425+12450.24+2029.5+3306.24 = 59732.01
D107: Итого по разделу | I107: =SUM(I98:I106) -> 458691651
A109: ВОР 02-01-03 — Архитектурные решения (АР) (102 поз.)
A110: 90 | B110: ВОР 02-01-03 — Архитектурные решения (АР) | C110: ВОР 2 | D110: Плитка керамогранитная, неполированная, многоцветная, толщина 10 мм | E110: 03-01/07.21П-АР.1 ГЧ л 1,2,4,17,26,34 (Файл: 03- 01_07.21П-АР.1.pdf, стр.: 1 2 4 17 26 34) | F110: м2 | G110: =Спецификация!G4126 -> 2179.427 | H110: =Спецификация!H4126 -> 3500 | I110: =Спецификация!I4126 -> 7627994.5 | J110: 4126 | K110: =IF(H110=0,"НЕТ ЦЕНЫ","проценено") -> проценено | L110: ВОР 02-01-03, нет в СО — в ВОРе: 133.46+555.645+79.713+388.528+307.204+714.877 = 2179.427
A111: 91 | B111: ВОР 02-01-03 — Архитектурные решения (АР) | C111: ВОР 3 | D111: Плиты теплоизоляционные из экструзионного пенополистирола, показатели пожарной опасности Г4, В2, Д3, Т2, плотность 30-39 кг/м3, теплопроводность при +10/+25 °C не более 0,034/0,035 Вт/(м*К), прочность на сжатие при 10% деформации не менее 0,4 МПа, толщина 40-100 мм | E111: 03-01/07.21П-АР.1 ГЧ л 1,2,4,17,26,34 (Файл: 03- 01_07.21П-АР.1.pdf, стр.: 1 2 4 17 26 34) | F111: м3 | G111: =Спецификация!G4127 -> 10.6768 | H111: =Спецификация!H4127 -> 14000 | I111: =Спецификация!I4127 -> 149475.2 | J111: 4127 | K111: =IF(H111=0,"НЕТ ЦЕНЫ","проценено") -> проценено | L111: ВОР 02-01-03, нет в СО
A112: 92 | B112: ВОР 02-01-03 — Архитектурные решения (АР) | C112: ВОР 5 | D112: Витраж из алюминиевого профиля шириной 45 мм с термовставкой, окрашенный, с двойным стеклопакетом толщиной 32 мм, с двумя поворотно-откидными створками размером 715x1390 мм, в комплекте с нащельниками и сливами | E112: 03-01/07.21П-АР.1 ГЧ л 1,2,4,17,26,34 (Файл: 03- 01_07.21П-АР.1.pdf, стр.: 1 2 4 17 26 34) | F112: м2 | G112: =Спецификация!G4128 -> 1481.35 | H112: =Спецификация!H4128 -> 58000 | I112: =Спецификация!I4128 -> 85918300 | J112: 4128 | K112: =IF(H112=0,"НЕТ ЦЕНЫ","проценено") -> проценено | L112: ВОР 02-01-03, нет в СО
A113: 93 | B113: ВОР 02-01-03 — Архитектурные решения (АР) | C113: ВОР 6 | D113: Витраж из алюминиевого профиля шириной 45 мм без термовставки, окрашенный, с одинарным остеклением, толщина стекла 6 мм и сэндвич-панель, толщина 10 мм, с двумя поворотно-откидными створками размером 715x1390 мм, в комплекте с нащельниками и сливами | E113: 03-01/07.21П-АР.1 ГЧ л 1,2,4,17,26,34 (Файл: 03- 01_07.21П-АР.1.pdf, стр.: 1 2 4 17 26 34) | F113: м2 | G113: =Спецификация!G4129 -> 1284.49 | H113: =Спецификация!H4129 -> 58000 | I113: =Спецификация!I4129 -> 74500420 | J113: 4129 | K113: =IF(H113=0,"НЕТ ЦЕНЫ","проценено") -> проценено | L113: ВОР 02-01-03, нет в СО — в ВОРе: 1253.06+31.43 = 1284.49
A114: 94 | B114: ВОР 02-01-03 — Архитектурные решения (АР) | C114: ВОР 8 | D114: Блок оконный из алюминиевого комбинированного профиля одинарной конструкции, с однокамерным стеклопакетом, одностворчатый, неоткрываемый | E114: 03-01/07.21П-АР.1 ГЧ л 1,2,4,17,26,34 (Файл: 03- 01_07.21П-АР.1.pdf, стр.: 1 2 4 17 26 34) | F114: м2 | G114: =Спецификация!G4130 -> 82.71 | H114: =Спецификация!H4130 -> 58000 | I114: =Спецификация!I4130 -> 4797180 | J114: 4130 | K114: =IF(H114=0,"НЕТ ЦЕНЫ","проценено") -> проценено | L114: ВОР 02-01-03, нет в СО
A115: 95 | B115: ВОР 02-01-03 — Архитектурные решения (АР) | C115: ВОР 10 | D115: Нащельник стальной оцинкованный с полимерным покрытием, толщина 0,5 мм | E115: 03-01/07.21П-АР.1 ГЧ л 1,2,4,17,26,34 (Файл: 03- 01 07.21П-АР.1.pdf, стр.: 1 2 4 17 26 34) | F115: м | G115: =Спецификация!G4131 -> 6613.82 | H115: =Спецификация!H4131 -> 200 | I115: =Спецификация!I4131 -> 1322764 | J115: 4131 | K115: =IF(H115=0,"НЕТ ЦЕНЫ","проценено") -> проценено | L115: ВОР 02-01-03, нет в СО — в ВОРе: 2211+4402.82 = 6613.82
A116: 96 | B116: ВОР 02-01-03 — Архитектурные решения (АР) | C116: ВОР 11 | D116: Конструкции навесной фасадной системы с воздушным зазором | E116: 03-01/07.21П-АР.1 ГЧ л 1,2,4,17,26,34 (Файл: 03- 01 07.21П-АР.1.pdf, стр.: 1 2 4 17 26 34) | F116: м2 | G116: =Спецификация!G4132 -> 2671.44 | H116: =Спецификация!H4132 -> 2400 | I116: =Спецификация!I4132 -> 6411456 | J116: 4132 | K116: =IF(H116=0,"НЕТ ЦЕНЫ","проценено") -> проценено | L116: ВОР 02-01-03, нет в СО
A117: 97 | B117: ВОР 02-01-03 — Архитектурные решения (АР) | C117: ВОР 12 | D117: Панели алюминиевые акустические перфорированные, диаметр отверстий 5-8 мм, толщина 1 мм | E117: 03-01/07.21П-АР.1 ГЧ л 1,2,4,17,26,34 (Файл: 03- 01_07.21П-АР.1.pdf, стр.: 1 2 4 17 26 34) | F117: м2 | G117: =Спецификация!G4133 -> 2671.44 | H117: =Спецификация!H4133 -> 2400 | I117: =Спецификация!I4133 -> 6411456 | J117: 4133 | K117: =IF(H117=0,"НЕТ ЦЕНЫ","проценено") -> проценено | L117: ВОР 02-01-03, нет в СО
A118: 98 | B118: ВОР 02-01-03 — Архитектурные решения (АР) | C118: ВОР 14 | D118: Сэндвич-панель трехслойная стеновая, сердцевина из базальтового волокна, металлическая облицовка с двух сторон толщиной 0,5 мм, тип покрытия полиэстер, внутренняя облицовка гладкая, наружная облицовка накатка, с симметричным замком, толщина 150 мм | E118: 03-01/07.21П-АР.1 ГЧ л 1,2,4,17,26,34 (Файл: 03- 01_07.21П-АР.1.pdf, стр.: 1 2 4 17 26 34) | F118: м2 | G118: =Спецификация!G4134 -> 4326.69 | H118: =Спецификация!H4134 -> 6500 | I118: =Спецификация!I4134 -> 28123485 | J118: 4134 | K118: =IF(H118=0,"НЕТ ЦЕНЫ","проценено") -> проценено | L118: ВОР 02-01-03, нет в СО — в ВОРе: 2371.44+1955.25 = 4326.69
A119: 99 | B119: ВОР 02-01-03 — Архитектурные решения (АР) | C119: ВОР 17 | D119: Витраж из нержавеющих профилей размером 100х50х2 мм, неоткрываемый, с одинарным стеклопакетом триплекс толщиной 12 мм | E119: 03-01/07.21П-АР.1 ГЧ л 1,2,4,17,26,34 (Файл: 03- 01_07.21П-АР.1.pdf, стр.: 1 2 4 17 26 34) | F119: м2 | G119: =Спецификация!G4135 -> 55.1 | H119: =Спецификация!H4135 -> 58000 | I119: =Спецификация!I4135 -> 3195800 | J119: 4135 | K119: =IF(H119=0,"НЕТ ЦЕНЫ","проценено") -> проценено | L119: ВОР 02-01-03, нет в СО
A120: 100 | B120: ВОР 02-01-03 — Архитектурные решения (АР) | C120: ВОР 19 | D120: Раствор готовый кладочный, цементный, М100 | E120: 03-01/07.21П-АР.1 ГЧ л 11,13,34 (Файл: 03- 01 07.21П-АР.1.pdf, стр.: 34 11 13) | F120: м3 | G120: =Спецификация!G4136 -> 344.7953 | H120: =Спецификация!H4136 -> 7000 | I120: =Спецификация!I4136 -> 2413567.1 | J120: 4136 | K120: =IF(H120=0,"НЕТ ЦЕНЫ","проценено") -> проценено | L120: ВОР 02-01-03, нет в СО — в ВОРе: 5.857×2 + 7.786 + 15.572 + 33.624 + 58.842 + 0.802 + 1.604 + 11.113 + 22.226 + 3.298 + 5.745 + 17.235 + 6.144 + 12.288 + 14.298 + 42.893 + 23.883 + 55.728 = 344.795
A121: 101 | B121: ВОР 02-01-03 — Архитектурные решения (АР) | C121: ВОР 23 | D121: Сетка стальная сварная из арматурной проволоки без покрытия, диаметр проволоки 5 мм, размер ячейки 200х200 мм | E121: 03-01/07.21П-АР.1 ГЧ л 11,13,34 (Файл: 03- 01_07.21П-АР.1.pdf, стр.: 34 11 13) | F121: м2 | G121: =Спецификация!G4137 -> 4693.2377 | H121: =Спецификация!H4137 -> 110 | I121: =Спецификация!I4137 -> 516256.15 | J121: 4137 | K121: =IF(H121=0,"НЕТ ЦЕНЫ","проценено") -> проценено | L121: ВОР 02-01-03, нет в СО — в ВОРе: 385.487 + 1664.722 + 39.703 + 155.631 + 550.197 + 284.436 + 310.999 + 304.192 + 707.869 + 290.001 = 4693.238
... A211: 191 | B211: ВОР 02-01-03 — Архитектурные решения (АР) | C211: ВОР 499 | D211: Лестница-стремянка металлическая, марка НТС 62-91-111а, ширина 600 мм, шаг ступеней 300 мм, высота от 1 до 6 м | E211: 03-01/07.21П-АР.1 ГЧ л 41 (Файл: 03-01_07.21П- АР.1.pdf стр.: 41) | F211: т | G211: =Спецификация!G4227 -> 1.9176 | H211: =Спецификация!H4227 -> 0 | I211: =Спецификация!I4227 -> 0 | J211: 4227 | K211: =IF(H211=0,"НЕТ ЦЕНЫ","проценено") -> НЕТ ЦЕНЫ | L211: ВОР 02-01-03, нет в СО
D212: Итого по разделу | I212: =SUM(I110:I211) -> 3.9628415e+08
A214: ВОР 02-01-11 — Технологические решения ТХ.2 (мебель, инвентарь, оборудование) (3 поз.)
A215: 192 | B215: ВОР 02-01-11 — Технологические решения ТХ.2 (мебель, инвентарь, оборудование) | C215: ВОР 408 | D215: Аппарат настенный, масса от 0,15 т до 0,2 т | E215: 03-01/07.21П-IX.2 (Файл: 03-01_07.21П—IX.2.pdf, стр.: 28) | F215: шт. | G215: =Спецификация!G4229 -> 2 | H215: =Спецификация!H4229 -> 0 | I215: =Спецификация!I4229 -> 0 | J215: 4229 | K215: =IF(H215=0,"НЕТ ЦЕНЫ","проценено") -> НЕТ ЦЕНЫ | L215: Есть в ВОР 02-01-11, в ТХ.2.СО отсутствует — закупать по этой строке
...

Sheet Сверка ТХ.2
A1: Сверка ВОР 02-01-11 (технологические решения) с оригиналом спецификации 03-01/07.21П-ТХ.2.СО
A2: Слева — позиции по СО (свод по всем 268 помещениям), справа — сумма количеств по строкам ВОРа, сопоставленным с этой позицией. Сопоставление по наименованию, поэтому у близких по названию позиций объём может быть отнесён к соседней строке — расхождения смотреть вместе с соседними строками.
A4: Наименование по ТХ.2.СО | B4: Ед. изм. | C4: Кол-во по СО | D4: Кол-во по ВОР | E4: Разница (ВОР − СО) | F4: Строк в ВОРе | G4: Статус
A5: Комплект принадлежностей для душевой: коврик нескользящий, полка для туалетных принадлежностей, вешалка настенная | B5: компл | C5: 1 | D5: 68 | E5: 67 | F5: 1 | G5: ВОР больше СО на 67
A6: Комплект принадлежностей для душевой: коврик нескользящий, занавеска, полка для туалетных принадлежностей, вешалка настенная | B6: шт | C6: 5 | D6: 68 | E6: 63 | F6: 1 | G6: ВОР больше СО на 63
A7: Диспенсер для бумажных полотенец. Сушилка для рук, настенная; Э: 1ф, 220В, 1.2кВт | B7: шт | C7: 25 | D7: 49 | E7: 24 | F7: 2 | G7: ВОР больше СО на 24
A8: Диспенсер для бумажных полотенец | B8: шт | C8: 17 | D8: 38 | E8: 21 | F8: 4 | G8: ВОР больше СО на 21
A9: Скамья гардеробная 854х390х475(h) мм | B9: шт | C9: 52 | D9: 68 | E9: 16 | F9: 5 | G9: ВОР больше СО на 16
A10: Стул для посетителей (материал обивки – к/з); 540х440х820(h) мм | B10: шт | C10: 75 | D10: 88 | E10: 13 | F10: 2 | G10: ВОР больше СО на 13
A11: Лампа настольная, 0,1 кВт, 220 В | B11: шт | C11: 11 | D11: 21 | E11: 10 | F11: 1 | G11: ВОР больше СО на 10
A12: Шкаф для раздевалок HPL пластик ТС 2-1 (2 секции) (64,5, В комплекте — верхняя полка, нижняя полка, штанга и крючок) (ДхВхШ) 624х1950х500 | B12: шт | C12: 20 | D12: 29 | E12: 9 | F12: 2 | G12: ВОР больше СО на 9
A13: Шкаф для раздевалок HPL ТС 1-10 300х500х1850 мм (запираемая распашная дверь, полка для головных уборов, перекладина для вешалки с крючками) | B13: шт | C13: 10 | D13: 18 | E13: 8 | F13: 1 | G13: ВОР больше СО на 8
A14: Многофункциональное устройство (копир/сканер/принтер), форматы А4 и А3; Э: 1 ф., 220 В, 0,6 кВт с возможностью печати фотографий | B14: шт | C14: 3 | D14: 11 | E14: 8 | F14: 1 | G14: ВОР больше СО на 8
A15: Комплект принадлежностей для душевой: коврик нескользящий, занавеска, полка для туалетных принадлежностей, вешалка настенная | B15: компл | C15: 62 | D15: 68 | E15: 6 | F15: 1 | G15: ВОР больше СО на 6
A16: Запарник с крышкой | B16: комплект | C16: 6 | D16: 12 | E16: 6 | F16: 2 | G16: ВОР больше СО на 6
... A45: Дозатор антисептика бесконтактный | B45: шт | C45: 6 | D45: 5 | E45: -1 | F45: 1 | G45: ВОР меньше СО на 1
A46: Скамья гардеробная; 854х390х475(h) мм | B46: шт | C46: 16 | F46: 0 | G46: нет прямой пары в ВОРе; близкая строка ВОРа отнесена к «Скамья гардеробная 854х390х475(h) мм» — проверить
A47: Стул для посетителей (материал обивки – к/з); 540х440х820 (h) мм | B47: шт | C47: 13 | F47: 0 | G47: нет прямой пары в ВОРе; близкая строка ВОРа отнесена к «Стул для посетителей (материал обивки – к/з);» — проверить
A48: Шкаф для раздевалок HPL пластик ТС 2-1 (2 секции) Один ярус (64,5, В комплекте — верхняя полка, нижняя полка, штанга и крючок) (ДхВхШ) 624х1950х500 | B48: шт | C48: 9 | F48: 0 | G48: нет прямой пары в ВОРе; близкая строка ВОРа отнесена к «Шкаф для раздевалок HPL пластик ТС 2-1 (2 сек» — проверить
A49: Телефон | B49: шт | C49: 7 | F49: 0 | G49: в ВОРе не найдено — позиция к закупке сверх ведомости (проверить)
A50: Банкетка параметрическая Габаритный размер 1000х450х450м; - Материал фанера ФСФ сорт 2/2 15мм; - Радиусная шлифовка кромки; - Обработка антисептическими составами | B50: шт | C50: 4 | F50: 0 | G50: нет прямой пары в ВОРе; близкая строка ВОРа отнесена к «Банкетка параметрическая. - Габаритный размер» — проверить
A51: Стеллаж сборный со сплошными полками (5 полок, нагрузка на полку 100 кг); 1000х600х2000(h) мм | B51: шт | C51: 4 | F51: 0 | G51: нет прямой пары в ВОРе; близкая строка ВОРа отнесена к «Стеллаж сборный со сплошными полками (5 полок» — проверить
A52: Укладка для оказания скорой медицинской помощи (общепрофильная) | B52: компл | C52: 2 | F52: 0 | G52: в ВОРе не найдено — позиция к закупке сверх ведомости (проверить)
A53: Стеллаж-шпилька кондитерский. Габариты: 560х520х1800 мм | B53: шт | C53: 2 | F53: 0 | G53: нет прямой пары в ВОРе; близкая строка ВОРа отнесена к «Стеллаж-шпилька Габариты: 560х520х1800 мм» — проверить
A54: Шкаф холодильный среднетемпературный Э1Ф, 220В, 169кВтч/год Габаритные: размеры: 595x650x1860мм | B54: шт | C54: 2 | F54: 0 | G54: нет прямой пары в ВОРе; близкая строка ВОРа отнесена к «Шкаф холодильный среднетемпературный Э1Ф, 220» — проверить
A55: Окно кассира для передачи билет/деньги Машина контрольно-кассовая; Э: 1 ф, 220 В, 0,25 кВт; Габариты 400х400х225 (h) мм | B55: шт | C55: 1 | F55: 0 | G55: нет прямой пары в ВОРе; близкая строка ВОРа отнесена к «Окно кассира для передачи Билет/деньги Машина» — проверить
A56: Лифт размером 1100х2100 Назначение и марка лифта: Пассажирский, для пожарных подразделений 1 Грузоподъёмность: кг 1000 2 Скорость движения кабины: м/с 1,0 - 1,6 3 Высота подъёма: м 4,5 4 Количество остановок/шахтных дверей: шт. 2 5 Характеристика электрической сети (напряжение, род тока) 6 Мощность потребляемая 11 кВт, Потребляемый ток в период пуска 36 А 7 Номинальный ток 22,5 А | B56: шт | C56: 1 | F56: 0 | G56: в ВОРе не найдено — позиция к закупке сверх ведомости (проверить)
A57: Защитная бросковая сетка на торцах и радиусах для арены 60х30м | B57: комплект | C57: 1 | F57: 0 | G57: нет прямой пары в ВОРе; близкая строка ВОРа отнесена к «Защитная бросковая сетка на торцах и радиусах» — проверить
... A62: Стеллаж сборный со сплошными полками (5 полок, нагрузка на полку 200 кг); 2000х600х2000(h) мм | B62: шт | C62: 1 | F62: 0 | G62: нет прямой пары в ВОРе; близкая строка ВОРа отнесена к «Стеллаж сборный со сплошными полками (5 полок» — проверить
A63: (объединено) Стол рабочий прямой; 1200х700х750(h) мм | B63: шт | C63: 0 | D63: 0 | E63: 0 | F63: 0 | G63: объединено со строкой выше — два написания одного наименования
A64: Габаритные размеры 1200х335х435 (ДхШхВ) мм Ванна моечная цельнотянутая односекционная (комплектуется сифоном), Внутренний размер емкости 400х500х250мм, материал – нержавеющая сталь. Каркас уголок - оцинкованная сталь. | B64: шт | C64: 1 | F64: 0 | G64: нет прямой пары в ВОРе; близкая строка ВОРа отнесена к «Ванна моечная цельнотянутая односекционная (к» — проверить
A65: сталь. Габаритные размеры примерно, 600х600х870мм Стерилизатор для ножей. Мощность лампы или ламп не менее 15Вт. Номинальное напряжение 230В±(23)В, рабочее напряжение 230В±(23)В. Габаритные размеры не более (500х155х620)мм. Предназначен для дезинфекции ножей. Процесс стерилизации происходит за счет работы ультрафиолетовой лампы. Кнопка включения и таймер находятся на передней и/или боковой панели стерилизатора. Таймер не менее чем на 50 минут. Вместе с изделием поставляется ультрафиолетовая лампа не менее 1 шт. Материал изготовления корпуса – нержавеющая пищевая сталь. Материал должен быть разрешен Минздравсоцразвитием России к контакту с пищевыми продуктами. | B65: шт | C65: 1 | F65: 0 | G65: нет прямой пары в ВОРе; близкая строка ВОРа отнесена к «Стерилизатор для ножей. Мощность лампы или ла» — проверить
A66: Зонт вытяжной пристенный АЛТЭК ЗВП 14/7 без фильтров, без подсветки, металл AISI 430, Габаритные размеры:1400 х 700 х 350 марка ЗВП 14/7, подключение осуществляется от системы вентиляции | B66: шт | C66: 1 | F66: 0 | G66: нет прямой пары в ВОРе; близкая строка ВОРа отнесена к «Зонт вытяжной пристенный АЛТЭК ЗВП 14/7 без ф» — проверить
A67: 700х700х2200 Контейнер 90л полипропилен d=42,5см h=85см с крышкой на колесах для пищевых отходов | B67: шт | C67: 1 | F67: 0 | G67: нет прямой пары в ВОРе; близкая строка ВОРа отнесена к «Контейнер 90л полипропилен d=42,5см h=85см с » — проверить
A68: мм Персональный компьютер (моноблок) с периферией, источник бесперебойного питания, сетевой фильтр шнур 3 м; Э: 1 ф., 220 В, 0,6 кВт, подключение к интернету, локальной сети | B68: шт | C68: 1 | F68: 0 | G68: нет прямой пары в ВОРе; близкая строка ВОРа отнесена к «Персональный компьютер (моноблок) с периферие» — проверить
A69: Диспенсер для бумажных полотенец Сушилка для рук, настенная; Э: 1ф, 220В, 1.2кВт | B69: шт | C69: 1 | F69: 0 | G69: в ВОРе не найдено — позиция к закупке сверх ведомости (проверить)
A70: Сетка заградительная капроновая, ячейка 40х40 мм, нить диаметром 5 мм, система для монтажа, Длина 60 м, высота 6,5 м | B70: 2 м | C70: 826 | D70: 826 | E70: 0 | F70: 1 | G70: сходится
A71: Зрительские кресла стационарные. Размеры кресла 500×500×980 мм шт | B71: шт | C71: 200 | D71: 200 | E71: 0 | F71: 1 | G71: сходится
A72: Шкафчик гардеробный для хоккеистов (для полевого игрока); 800х600х2000(h) мм в комплекте со скамьей | B72: шт | C72: 138 | D72: 138 | E72: 0 | F72: 3 | G72: сходится
A73: Дозатор для жидкого мыла | B73: шт | C73: 60 | D73: 60 | E73: 0 | F73: 3 | G73: сходится
A74: Шкаф для раздевалок ТС 6-8 (3 секции); HPL; Высота (мм) — 1800. Ширина (мм) — 400. Глубина (мм) – 500. | B74: шт | C74: 50 | D74: 50 | E74: 0 | F74: 1 | G74: сходится
A75: Кресло с пюпитром, крепление к полу | B75: шт | C75: 50 | D75: 50 | E75: 0 | F75: 1 | G75: сходится
A76: Зеркало 900*1400 мм по двум стенам зала | B76: шт | C76: 48 | D76: 48 | E76: 0 | F76: 1 | G76: сходится
A77: Диспенсер для туалетной бумаги в рулонах | B77: шт | C77: 46 | D77: 46 | E77: 0 | F77: 3 | G77: сходится
A78: Ёршик для унитаза, напольный | B78: шт | C78: 46 | D78: 46 | E78: 0 | F78: 1 | G78: сходится
A79: Шкаф сушильный инфракрасный для сушки одежды и обуви, на 4 комплекта (металлический); М.О. ø100 мм, 180 м3/ч; Э: 1ф, 220В, 1.9А, 0.65кВт; 805х670х1900(h) мм | B79: шт | C79: 42 | D79: 42 | E79: 0 | F79: 3 | G79: сходится
A80: Зеркало антивандальное настенное 800*600мм | B80: шт | C80: 40 | D80: 40 | E80: 0 | F80: 1 | G80: сходится
A81: Протектор настенный, высота 2 м, жесткое основание (ДСП или фанера), толщина 50 мм, обтяжка ПВХ ткань или кожзаменитель, крепление в комплекте | B81: шт | C81: 40 | D81: 40 | E81: 0 | F81: 1 | G81: сходится
... A288: Проектор Acer X1328WHn | B288: шт | C288: 1 | D288: 1 | E288: 0 | F288: 1 | G288: сходится
A290: Позиции ВОР 02-01-11, которым пары в ТХ.2.СО не нашлось (в книге помечены «нет в СО»)
A291: Аппарат настенный, масса от 0,15 т до 0,2 т | B291: шт. | D291: 2 | F291: 1 | G291: нет в ТХ.2.СО — проверить
A292: Арматура муфтовая с ручным приводом или без привода водопроводная на номинальное давление до 10 МПа, номинальный диаметр: 50 мм | B292: шт. | D292: 2 | F292: 1 | G292: нет в ТХ.2.СО — проверить

Sheet Правки
A1: ВСЕ ПРАВКИ, ВНЕСЁННЫЕ В ЛИСТ «СПЕЦИФИКАЦИЯ» — можно проверить каждую и при желании удалить этот лист
A2: Строка | B2: Колонка | C2: Было | D2: Стало | E2: Что сделано
A3: 3 | B3: K — Примечание | C3: ВОР 01-01-01, логистика | D3: ВОР 01-01-01, логистика; Источник: 03-01/07.21П-ООС.ТЧ. л 47 (Файл: 03-01_07.21П- ПЗУ.pdf, стр.: 178 179) | E3: ссылка на документ перенесена из «Тип, марка» в примечание
A4: 3 | B4: C — Тип, марка | C4: 03-01/07.21П-ООС.ТЧ. л 47 (Файл: 03-01_07.21П- ПЗУ.pdf, стр.: 178 179) | E4: ссылка на документ убрана из «Тип, марка»
A5: 4 | B5: K — Примечание | C5: ВОР 01-01-01, логистика | D5: ВОР 01-01-01, логистика; Источник: 03-01/07.21П-ПОС.ТЧ. Приложение Д л. 179,187 (Файл: 03-01_07.21П-КР.pdf, стр.: 179) | E5: ссылка на документ перенесена из «Тип, марка» в примечание
A6: 4 | B6: C — Тип, марка | C6: 03-01/07.21П-ПОС.ТЧ. Приложение Д л. 179,187 (Файл: 03-01_07.21П-КР.pdf, стр.: 179) | E6: ссылка на документ убрана из «Тип, марка»
A7: 5 | B7: K — Примечание | C7: ВОР 04-01-01, логистика | D7: ВОР 04-01-01, логистика; Источник: 03-01/07.21П-ИОС.1.5. л.10 (Файл: 03-01_07.21П- ИОС.1.5.pdf, стр.: 10) | E7: ссылка на документ перенесена из «Тип, марка» в примечание
A8: 5 | B8: C — Тип, марка | C8: 03-01/07.21П-ИОС.1.5. л.10 (Файл: 03-01_07.21П- ИОС.1.5.pdf, стр.: 10) | E8: ссылка на документ убрана из «Тип, марка»
A9: 6 | B9: K — Примечание | C9: ВОР 06-01-01, логистика | D9: ВОР 06-01-01, логистика; Источник: 03-01/07.21П-ПОС.ТЧ. Приложение Д. л. 179 (Файл: 03-01_07.21П-ПОС.pdf, стр.: 1) | E9: ссылка на документ перенесена из «Тип, марка» в примечание
A10: 6 | B10: C — Тип, марка | C10: 03-01/07.21П-ПОС.ТЧ. Приложение Д. л. 179 (Файл: 03-01_07.21П-ПОС.pdf, стр.: 1) | E10: ссылка на документ убрана из «Тип, марка»
A11: 7 | B11: K — Примечание | C11: ВОР 06-01-01, логистика | D11: ВОР 06-01-01, логистика; Источник: 03-01/07.21П-ПОС.ТЧ. Приложение Д. л. 179 (Файл: 03-01_07.21П-ПОС.pdf, стр.: 1) | E11: ссылка на документ перенесена из «Тип, марка» в примечание
A12: 7 | B12: C — Тип, марка | C12: 03-01/07.21П-ПОС.ТЧ. Приложение Д. л. 179 (Файл: 03-01_07.21П-ПОС.pdf, стр.: 1) | E12: ссылка на документ убрана из «Тип, марка»
A13: 8 | B13: K — Примечание | C13: ВОР 06-01-01, логистика | D13: ВОР 06-01-01, логистика; Источник: 03-01/07.21П-ПОС.ТЧ. Приложение Д. л. 180 (Файл: 03-01_07.21П-ПОС.pdf, стр.: 1) | E13: ссылка на документ перенесена из «Тип, марка» в примечание
A14: 8 | B14: C — Тип, марка | C14: 03-01/07.21П-ПОС.ТЧ. Приложение Д. л. 180 (Файл: 03-01_07.21П-ПОС.pdf, стр.: 1) | E14: ссылка на документ убрана из «Тип, марка»
A15: 9 | B15: K — Примечание | C15: ВОР 06-01-02, логистика | D15: ВОР 06-01-02, логистика; Источник: 03-01/07.21П-ПОС.ТЧ. Приложение Д. л. 186 (Файл: 03-01_07.21П-ПОС.pdf, стр.: 1) | E15: ссылка на документ перенесена из «Тип, марка» в примечание
A16: 9 | B16: C — Тип, марка | C16: 03-01/07.21П-ПОС.ТЧ. Приложение Д. л. 186 (Файл: 03-01_07.21П-ПОС.pdf, стр.: 1) | E16: ссылка на документ убрана из «Тип, марка»
A17: 10 | B17: K — Примечание | C17: ВОР 06-01-02, логистика | D17: ВОР 06-01-02, логистика; Источник: 03-01/07.21П-ПОС.ТЧ. Приложение Д. л. 181-182 (Файл: 03-01_07.21П-ПОС.pdf, стр.: 1) | E17: ссылка на документ перенесена из «Тип, марка» в примечание
A18: 10 | B18: C — Тип, марка | C18: 03-01/07.21П-ПОС.ТЧ. Приложение Д. л. 181-182 (Файл: 03-01_07.21П-ПОС.pdf, стр.: 1) | E18: ссылка на документ убрана из «Тип, марка»
A19: 11 | B19: K — Примечание | C19: ВОР 06-01-02, логистика | D19: ВОР 06-01-02, логистика; Источник: 03-01/07.21П-ПОС.ТЧ. Приложение Д. л. 186 (Файл: 03-01_07.21П-ПОС.pdf, стр.: 1) | E19: ссылка на документ перенесена из «Тип, марка» в примечание
A20: 11 | B20: C — Тип, марка | C20: 03-01/07.21П-ПОС.ТЧ. Приложение Д. л. 186 (Файл: 03-01_07.21П-ПОС.pdf, стр.: 1) | E20: ссылка на документ убрана из «Тип, марка»
A21: 12 | B21: K — Примечание | C21: ВОР 06-01-02, логистика | D21: ВОР 06-01-02, логистика; Источник: 03-01/07.21П-ПОС.ТЧ. Приложение Д. л. 181-182 (Файл: 03-01_07.21П-ПОС.pdf, стр.: 1) | E21: ссылка на документ перенесена из «Тип, марка» в примечание
A22: 12 | B22: C — Тип, марка | C22: 03-01/07.21П-ПОС.ТЧ. Приложение Д. л. 181-182 (Файл: 03-01_07.21П-ПОС.pdf, стр.: 1) | E22: ссылка на документ убрана из «Тип, марка»
A23: 13 | B23: K — Примечание | C23: ВОР 06-01-02, логистика | D23: ВОР 06-01-02, логистика; Источник: 03-01/07.21П-ПОС.ТЧ. Приложение Д. л. 186 (Файл: 03-01_07.21П-ПОС.pdf, стр.: 1) | E23: ссылка на документ перенесена из «Тип, марка» в примечание
A24: 13 | B24: C — Тип, марка | C24: 03-01/07.21П-ПОС.ТЧ. Приложение Д. л. 186 (Файл: 03-01_07.21П-ПОС.pdf, стр.: 1) | E24: ссылка на документ убрана из «Тип, марка»
A25: 14 | B25: K — Примечание | C25: ВОР 06-01-02, логистика | D25: ВОР 06-01-02, логистика; Источник: 03-01/07.21П-ПОС.ТЧ. Приложение Д. л. 184 (Файл: 03-01_07.21П-ПОС.pdf, стр.: 1) | E25: ссылка на документ перенесена из «Тип, марка» в примечание
A26: 14 | B26: C — Тип, марка | C26: 03-01/07.21П-ПОС.ТЧ. Приложение Д. л. 184 (Файл: 03-01_07.21П-ПОС.pdf, стр.: 1) | E26: ссылка на документ убрана из «Тип, марка»
A27: 15 | B27: K — Примечание | C27: ВОР 06-01-04, логистика | D27: ВОР 06-01-04, логистика; Источник: 03-01/07.21П-ПОС.ТЧ. Приложение Д л. 186 (Файл: 03-01_07.21П-ИОС4.4.pdf, стр.: 186) | E27: ссылка на документ перенесена из «Тип, марка» в примечание
A28: 15 | B28: C — Тип, марка | C28: 03-01/07.21П-ПОС.ТЧ. Приложение Д л. 186 (Файл: 03-01_07.21П-ИОС4.4.pdf, стр.: 186) | E28: ссылка на документ убрана из «Тип, марка»
A29: 16 | B29: K — Примечание | C29: ВОР 07-01-02, логистика | D29: ВОР 07-01-02, логистика; Источник: 03-01/07.21П-ПЗУ.ГЧ л.6 (Файл: 03-01_07.21П- ПЗУ.pdf, стр.: 55) | E29: ссылка на документ перенесена из «Тип, марка» в примечание
A30: 16 | B30: C — Тип, марка | C30: 03-01/07.21П-ПЗУ.ГЧ л.6 (Файл: 03-01_07.21П- ПЗУ.pdf.pdf, стр.: 55) | E30: ссылка на документ убрана из «Тип, марка»
A31: 17 | B31: K — Примечание | C31: ВОР 07-01-04, логистика | D31: ВОР 07-01-04, логистика; Источник: 03-01/07.21П-ИОС.1.4.ГЧ л.2 (Файл: 03-01_07.21П- ИОС.1.4.pdf, стр.: 18 19 20 21) | E31: ссылка на документ перенесена из «Тип, марка» в примечание
A32: 17 | B32: C — Тип, марка | C32: 03-01/07.21П-ИОС.1.4.ГЧ л.2 (Файл: 03-01_07.21П- ИОС.1.4.pdf, стр.: 18 19 20 21) | E32: ссылка на документ убрана из «Тип, марка»
A33: 384 | B33: K — Примечание | C33: ВОР, нет в СО | D33: ВОР, нет в СО; Источник: 03-01/07.21П-ИОС 2.1.ГЧ Спецификация (Файл: 03- 01_07.21П-ИОС.2.pdf стр.: 1 2 3 4 5 6) | E33: ссылка на документ перенесена из «Тип, марка» в примечание
A34: 384 | B34: C — Тип, марка | C34: 03-01/07.21П-ИОС 2.1.ГЧ Спецификация (Файл: 03- 01_07.21П-ИОС.2.pdf стр.: 1 2 3 4 5 6) | E34: ссылка на документ убрана из «Тип, марка»
A35: 385 | B35: K — Примечание | C35: ВОР, нет в СО | D35: ВОР, нет в СО; Источник: 03-01/07.21П-ИОС 2.1.ГЧ Спецификация (Файл: 03- 01_07.21П-ИОС.2.pdf стр.: 1 2 3 4 5 6) | E35: ссылка на документ перенесена из «Тип, марка» в примечание
A36: 385 | B36: C — Тип, марка | C36: 03-01/07.21П-ИОС 2.1.ГЧ Спецификация (Файл: 03- 01_07.21П-ИОС.2.pdf стр.: 1 2 3 4 5 6) | E36: ссылка на документ убрана из «Тип, марка»
A37: 386 | B37: K — Примечание | C37: ВОР, нет в СО | D37: ВОР, нет в СО; Источник: 03-01/07.21П-ИОС 2.1.ГЧ Спецификация (Файл: 03- 01_07.21П-ИОС.2.pdf стр.: 1 2 3 4 5 6) | E37: ссылка на документ перенесена из «Тип, марка» в примечание
A38: 386 | B38: C — Тип, марка | C38: 03-01/07.21П-ИОС 2.1.ГЧ Спецификация (Файл: 03- 01_07.21П-ИОС.2.pdf стр.: 1 2 3 4 5 6) | E38: ссылка на документ убрана из «Тип, марка»
A39: 387 | B39: K — Примечание | C39: ВОР, нет в СО | D39: ВОР, нет в СО; Источник: 03-01/07.21П-ИОС 2.1.ГЧ Спецификация (Файл: 03- 01_07.21П-ИОС.2.pdf стр.: 1 2 3 4 5 6) | E39: ссылка на документ перенесена из «Тип, марка» в примечание
A40: 387 | B40: C — Тип, марка | C40: 03-01/07.21П-ИОС 2.1.ГЧ Спецификация (Файл: 03- 01_07.21П-ИОС.2.pdf стр.: 1 2 3 4 5 6) | E40: ссылка на документ убрана из «Тип, марка»
A41: 388 | B41: K — Примечание | C41: ВОР, нет в СО | D41: ВОР, нет в СО; Источник: 03-01/07.21П-ИОС 2.1.ГЧ Спецификация (Файл: 03- 01_07.21П-ИОС.2.pdf стр.: 1 2 3 4 5 6) | E41: ссылка на документ перенесена из «Тип, марка» в примечание
A42: 388 | B42: C — Тип, марка | C42: 03-01/07.21П-ИОС 2.1.ГЧ Спецификация (Файл: 03- 01_07.21П-ИОС.2.pdf стр.: 1 2 3 4 5 6) | E42: ссылка на документ убрана из «Тип, марка»
A43: 389 | B43: K — Примечание | C43: ВОР, нет в СО | D43: ВОР, нет в СО; Источник: 03-01/07.21П-ИОС 2.1.ГЧ Спецификация (Файл: 03- 01 07.21П-ИОС.2.pdf стр.: 1 2 3 4 5 6) | E43: ссылка на документ перенесена из «Тип, марка» в примечание
A44: 389 | B44: C — Тип, марка | C44: 03-01/07.21П-ИОС 2.1.ГЧ Спецификация (Файл: 03- 01 07.21П-ИОС.2.pdf стр.: 1 2 3 4 5 6) | E44: ссылка на документ убрана из «Тип, марка»
A45: 390 | B45: K — Примечание | C45: ВОР, нет в СО | D45: ВОР, нет в СО; Источник: 03-01/07.21П-ИОС 2.1.ГЧ Спецификация (Файл: 03- 01 07.21П-ИОС.2.pdf стр.: 1 2 3 4 5 6) | E45: ссылка на документ перенесена из «Тип, марка» в примечание
A46: 390 | B46: C — Тип, марка | C46: 03-01/07.21П-ИОС 2.1.ГЧ Спецификация (Файл: 03- 01 07.21П-ИОС.2.pdf стр.: 1 2 3 4 5 6) | E46: ссылка на документ убрана из «Тип, марка»
A47: 391 | B47: K — Примечание | C47: ВОР, нет в СО | D47: ВОР, нет в СО; Источник: 03-01/07.21П-ИОС 2.1.ГЧ Спецификация (Файл: 03- 01_07.21П-ИОС.2.pdf стр.: 1 2 3 4 5 6) | E47: ссылка на документ перенесена из «Тип, марка» в примечание
A48: 391 | B48: C — Тип, марка | C48: 03-01/07.21П-ИОС 2.1.ГЧ Спецификация (Файл: 03- 01_07.21П-ИОС.2.pdf стр.: 1 2 3 4 5 6) | E48: ссылка на документ убрана из «Тип, марка»
A49: 392 | B49: K — Примечание | C49: ВОР, нет в СО | D49: ВОР, нет в СО; Источник: 03-01/07.21П-ИОС 2.1.ГЧ Спецификация (Файл: 03- 01 07.21П-ИОС.2.pdf стр.: 1 2 3 4 5 6) | E49: ссылка на документ перенесена из «Тип, марка» в примечание
A50: 392 | B50: C — Тип, марка | C50: 03-01/07.21П-ИОС 2.1.ГЧ Спецификация (Файл: 03- 01 07.21П-ИОС.2.pdf стр.: 1 2 3 4 5 6) | E50: ссылка на документ убрана из «Тип, марка»
A51: 393 | B51: K — Примечание | C51: ВОР, нет в СО | D51: ВОР, нет в СО; Источник: 03-01/07.21П-ИОС 2.1.ГЧ Спецификация (Файл: 03- 01 07.21П-ИОС.2.pdf стр.: 1 2 3 4 5 6) | E51: ссылка на документ перенесена из «Тип, марка» в примечание
A52: 393 | B52: C — Тип, марка | C52: 03-01/07.21П-ИОС 2.1.ГЧ Спецификация (Файл: 03- 01 07.21П-ИОС.2.pdf стр.: 1 2 3 4 5 6) | E52: ссылка на документ убрана из «Тип, марка»
A53: 394 | B53: K — Примечание | C53: ВОР, нет в СО | D53: ВОР, нет в СО; Источник: 03-01/07.21П-ИОС 2.1.ГЧ Спецификация (Файл: 03- 01 07.21П-ИОС.2.pdf стр.: 1 2 3 4 5 6) | E53: ссылка на документ перенесена из «Тип, марка» в примечание
A54: 394 | B54: C — Тип, марка | C54: 03-01/07.21П-ИОС 2.1.ГЧ Спецификация (Файл: 03- 01 07.21П-ИОС.2.pdf стр.: 1 2 3 4 5 6) | E54: ссылка на документ убрана из «Тип, марка»
A55: 395 | B55: K — Примечание | C55: ВОР, нет в СО | D55: ВОР, нет в СО; Источник: 03-01/07.21П-ИОС 2.1.ГЧ Спецификация (Файл: 03- 01 07.21П-ИОС.2.pdf стр.: 1 2 3 4 5 6) | E55: ссылка на документ перенесена из «Тип, марка» в примечание
A56: 395 | B56: C — Тип, марка | C56: 03-01/07.21П-ИОС 2.1.ГЧ Спецификация (Файл: 03- 01 07.21П-ИОС.2.pdf стр.: 1 2 3 4 5 6) | E56: ссылка на документ убрана из «Тип, марка»
A57: 396 | B57: K — Примечание | C57: ВОР, нет в СО | D57: ВОР, нет в СО; Источник: 03-01/07.21П-ИОС 2.1.ГЧ Спецификация (Файл: 03- 01_07.21П-ИОС.2.pdf стр.: 1 2 3 4 5 6) | E57: ссылка на документ перенесена из «Тип, марка» в примечание
A58: 396 | B58: C — Тип, марка | C58: 03-01/07.21П-ИОС 2.1.ГЧ Спецификация (Файл: 03- 01_07.21П-ИОС.2.pdf стр.: 1 2 3 4 5 6) | E58: ссылка на документ убрана из «Тип, марка»
A59: 397 | B59: K — Примечание | C59: ВОР, нет в СО | D59: ВОР, нет в СО; Источник: 03-01/07.21П-ИОС 2.1.ГЧ Спецификация (Файл: 03- 01_07.21П-ИОС.2.pdf стр.: 1 2 3 4 5 6) | E59: ссылка на документ перенесена из «Тип, марка» в примечание
A60: 397 | B60: C — Тип, марка | C60: 03-01/07.21П-ИОС 2.1.ГЧ Спецификация (Файл: 03- 01_07.21П-ИОС.2.pdf стр.: 1 2 3 4 5 6) | E60: ссылка на документ убрана из «Тип, марка»
A61: 398 | B61: K — Примечание | C61: ВОР, нет в СО | D61: ВОР, нет в СО; Источник: 03-01/07.21П-ИОС 2.1.ГЧ Спецификация (Файл: 03- 01 07.21П-ИОС.2.pdf стр.: 1 2 3 4 5 6) | E61: ссылка на документ перенесена из «Тип, марка» в примечание
A62: 398 | B62: C — Тип, марка | C62: 03-01/07.21П-ИОС 2.1.ГЧ Спецификация (Файл: 03- 01 07.21П-ИОС.2.pdf стр.: 1 2 3 4 5 6) | E62: ссылка на документ убрана из «Тип, марка»
A63: 399 | B63: K — Примечание | C63: ВОР, нет в СО | D63: ВОР, нет в СО; Источник: 03-01/07.21П-ИОС 2.1.ГЧ Спецификация (Файл: 03- 01 07.21П-ИОС.2.pdf стр.: 1 2 3 4 5 6) | E63: ссылка на документ перенесена из «Тип, марка» в примечание
A64: 399 | B64: C — Тип, марка | C64: 03-01/07.21П-ИОС 2.1.ГЧ Спецификация (Файл: 03- 01 07.21П-ИОС.2.pdf стр.: 1 2 3 4 5 6) | E64: ссылка на документ убрана из «Тип, марка»
A65: 400 | B65: K — Примечание | C65: ВОР, нет в СО | D65: ВОР, нет в СО; Источник: 03-01/07.21П-ИОС 2.1.ГЧ Спецификация (Файл: 03- 01_07.21П-ИОС.2.pdf стр.: 1 2 3 4 5 6) | E65: ссылка на документ перенесена из «Тип, марка» в примечание
A66: 400 | B66: C — Тип, марка | C66: 03-01/07.21П-ИОС 2.1.ГЧ Спецификация (Файл: 03- 01_07.21П-ИОС.2.pdf стр.: 1 2 3 4 5 6) | E66: ссылка на документ убрана из «Тип, марка»
A67: 401 | B67: K — Примечание | C67: ВОР, нет в СО | D67: ВОР, нет в СО; Источник: 03-01/07.21П-ИОС 2.1.ГЧ Спецификация (Файл: 03- 01 07.21П-ИОС.2.pdf стр.: 1 2 3 4 5 6) | E67: ссылка на документ перенесена из «Тип, марка» в примечание
A68: 401 | B68: C — Тип, марка | C68: 03-01/07.21П-ИОС 2.1.ГЧ Спецификация (Файл: 03- 01 07.21П-ИОС.2.pdf стр.: 1 2 3 4 5 6) | E68: ссылка на документ убрана из «Тип, марка»
A69: 402 | B69: K — Примечание | C69: ВОР, нет в СО | D69: ВОР, нет в СО; Источник: 03-01/07.21П-ИОС 2.1.ГЧ Спецификация (Файл: 03- 01 07.21П-ИОС.2.pdf стр.: 1 2 3 4 5 6) | E69: ссылка на документ перенесена из «Тип, марка» в примечание
A70: 402 | B70: C — Тип, марка | C70: 03-01/07.21П-ИОС 2.1.ГЧ Спецификация (Файл: 03- 01 07.21П-ИОС.2.pdf стр.: 1 2 3 4 5 6) | E70: ссылка на документ убрана из «Тип, марка»
A71: 403 | B71: K — Примечание | C71: ВОР, нет в СО | D71: ВОР, нет в СО; Источник: 03-01/07.21П-ИОС 2.1.ГЧ Спецификация (Файл: 03- 01 07.21П-ИОС.2.pdf стр.: 1 2 3 4 5 6) | E71: ссылка на документ перенесена из «Тип, марка» в примечание
A72: 403 | B72: C — Тип, марка | C72: 03-01/07.21П-ИОС 2.1.ГЧ Спецификация (Файл: 03- 01 07.21П-ИОС.2.pdf стр.: 1 2 3 4 5 6) | E72: ссылка на документ убрана из «Тип, марка»
A73: 404 | B73: K — Примечание | C73: ВОР, нет в СО | D73: ВОР, нет в СО; Источник: 03-01/07.21П-ИОС 2.1.ГЧ Спецификация (Файл: 03- 01 07.21П-ИОС.2.pdf стр.: 1 2 3 4 5 6) | E73: ссылка на документ перенесена из «Тип, марка» в примечание
A74: 404 | B74: C — Тип, марка | C74: 03-01/07.21П-ИОС 2.1.ГЧ Спецификация (Файл: 03- 01 07.21П-ИОС.2.pdf стр.: 1 2 3 4 5 6) | E74: ссылка на документ убрана из «Тип, марка»
A75: 405 | B75: K — Примечание | C75: ВОР, нет в СО | D75: ВОР, нет в СО; Источник: 03-01/07.21П-ИОС 2.1.ГЧ Спецификация (Файл: 03- 01_07.21П-ИОС.2.pdf стр.: 1 2 3 4 5 6) | E75: ссылка на документ перенесена из «Тип, марка» в примечание
A76: 405 | B76: C — Тип, марка | C76: 03-01/07.21П-ИОС 2.1.ГЧ Спецификация (Файл: 03- 01_07.21П-ИОС.2.pdf стр.: 1 2 3 4 5 6) | E76: ссылка на документ убрана из «Тип, марка»
A77: 406 | B77: K — Примечание | C77: ВОР, нет в СО | D77: ВОР, нет в СО; Источник: 03-01/07.21П-ИОС 2.1.ГЧ Спецификация (Файл: 03- 01 07.21П-ИОС.2.pdf стр.: 1 2 3 4 5 6) | E77: ссылка на документ перенесена из «Тип, марка» в примечание
A78: 406 | B78: C — Тип, марка | C78: 03-01/07.21П-ИОС 2.1.ГЧ Спецификация (Файл: 03- 01 07.21П-ИОС.2.pdf стр.: 1 2 3 4 5 6) | E78: ссылка на документ убрана из «Тип, марка»
A79: 407 | B79: K — Примечание | C79: ВОР, нет в СО | D79: ВОР, нет в СО; Источник: 03-01/07.21П-ИОС 2.1.ГЧ Спецификация (Файл: 03- 01 07.21П-ИОС.2.pdf стр.: 1 2 3 4 5 6) | E79: ссылка на документ перенесена из «Тип, марка» в примечание
A80: 407 | B80: C — Тип, марка | C80: 03-01/07.21П-ИОС 2.1.ГЧ Спецификация (Файл: 03- 01 07.21П-ИОС.2.pdf стр.: 1 2 3 4 5 6) | E80: ссылка на документ убрана из «Тип, марка»
A81: 408 | B81: K — Примечание | C81: ВОР, нет в СО | D81: ВОР, нет в СО; Источник: 03-01/07.21П-ИОС 2.1.ГЧ Спецификация (Файл: 03- 01_07.21П-ИОС.2.pdf стр.: 1 2 3 4 5 6) | E81: ссылка на документ перенесена из «Тип, марка» в примечание
A82: 408 | B82: C — Тип, марка | C82: 03-01/07.21П-ИОС 2.1.ГЧ Спецификация (Файл: 03- 01_07.21П-ИОС.2.pdf стр.: 1 2 3 4 5 6) | E82: ссылка на документ убрана из «Тип, марка»
A83: 423 | B83: K — Примечание | C83: ВОР, нет в СО | D83: ВОР, нет в СО; Источник: 03-01/07.21П-ИОС 3.1 ГЧ. Спецификация л. 1 (Файл: 03-01_07.21П-ИОС3.1.pdf, стр.: 1) | E83: ссылка на документ перенесена из «Тип, марка» в примечание
A84: 423 | B84: C — Тип, марка | C84: 03-01/07.21П-ИОС 3.1 ГЧ. Спецификация л. 1 (Файл: 03-01_07.21П-ИОС3.1.pdf, стр.: 1) | E84: ссылка на документ убрана из «Тип, марка»
A85: 424 | B85: K — Примечание | C85: ВОР, нет в СО | D85: ВОР, нет в СО; Источник: 03-01/07.21П-ИОС 3.1 ГЧ. Спецификация л. 1 (Файл: 03-01_07.21П-ИОС3.1.pdf, стр.: 1) | E85: ссылка на документ перенесена из «Тип, марка» в примечание
A86: 424 | B86: C — Тип, марка | C86: 03-01/07.21П-ИОС 3.1 ГЧ. Спецификация л. 1 (Файл: 03-01_07.21П-ИОС3.1.pdf, стр.: 1) | E86: ссылка на документ убрана из «Тип, марка»
A87: 425 | B87: K — Примечание | C87: ВОР, нет в СО | D87: ВОР, нет в СО; Источник: 03-01/07.21П-ИОС 3.1 ГЧ. Спецификация л. 2 (Файл: 03-01_07.21П-ИОС3.1.pdf, стр.: 1) | E87: ссылка на документ перенесена из «Тип, марка» в примечание
A88: 425 | B88: C — Тип, марка | C88: 03-01/07.21П-ИОС 3.1 ГЧ. Спецификация л. 2 (Файл: 03-01_07.21П-ИОС3.1.pdf, стр.: 1) | E88: ссылка на документ убрана из «Тип, марка»
A89: 426 | B89: K — Примечание | C89: ВОР, нет в СО | D89: ВОР, нет в СО; Источник: 03-01/07.21П-ИОС 3.1 ГЧ. Спецификация л. 2 (Файл: 03-01_07.21П-ИОС3.1.pdf, стр.: 1) | E89: ссылка на документ перенесена из «Тип, марка» в примечание
A90: 426 | B90: C — Тип, марка | C90: 03-01/07.21П-ИОС 3.1 ГЧ. Спецификация л. 2 (Файл: 03-01_07.21П-ИОС3.1.pdf, стр.: 1) | E90: ссылка на документ убрана из «Тип, марка»
A91: 427 | B91: K — Примечание | C91: ВОР, нет в СО | D91: ВОР, нет в СО; Источник: 03-01/07.21П-ИОС 3.1 ГЧ. Спецификация л. 2 (Файл: 03-01_07.21П-ИОС3.1.pdf, стр.: 1) | E91: ссылка на документ перенесена из «Тип, марка» в примечание
A92: 427 | B92: C — Тип, марка | C92: 03-01/07.21П-ИОС 3.1 ГЧ. Спецификация л. 2 (Файл: 03-01_07.21П-ИОС3.1.pdf, стр.: 1) | E92: ссылка на документ убрана из «Тип, марка»
A93: 428 | B93: K — Примечание | C93: ВОР, нет в СО | D93: ВОР, нет в СО; Источник: 03-01/07.21П-ИОС 3.1 ГЧ. Спецификация л. 2 (Файл: 03-01/07.21П-ИОС3.1.pdf, стр.: 1) | E93: ссылка на документ перенесена из «Тип, марка» в примечание
A94: 428 | B94: C — Тип, марка | C94: 03-01/07.21П-ИОС 3.1 ГЧ. Спецификация л. 2 (Файл: 03-01 07.21П-ИОС3.1.pdf, стр.: 1) | E94: ссылка на документ убрана из «Тип, марка»
A95: 429 | B95: K — Примечание | C95: ВОР, нет в СО | D95: ВОР, нет в СО; Источник: 03-01/07.21П-ИОС 3.1 ГЧ. Спецификация л. 2 (Файл: 03-01/07.21П-ИОС3.1.pdf, стр.: 1) | E95: ссылка на документ перенесена из «Тип, марка» в примечание
A96: 429 | B96: C — Тип, марка | C96: 03-01/07.21П-ИОС 3.1 ГЧ. Спецификация л. 2 (Файл: 03-01 07.21П-ИОС3.1.pdf, стр.: 1) | E96: ссылка на документ убрана из «Тип, марка»
A97: 430 | B97: K — Примечание | C97: ВОР, нет в СО | D97: ВОР, нет в СО; Источник: 03-01/07.21П-ИОС 3.1 ГЧ. Спецификация л. 2 (Файл: 03-01/07.21П-ИОС3.1.pdf, стр.: 1) | E97: ссылка на документ перенесена из «Тип, марка» в примечание
A98: 430 | B98: C — Тип, марка | C98: 03-01/07.21П-ИОС 3.1 ГЧ. Спецификация л. 2 (Файл: 03-01 07.21П-ИОС3.1.pdf, стр.: 1) | E98: ссылка на документ убрана из «Тип, марка»
A99: 431 | B99: K — Примечание | C99: ВОР, нет в СО | D99: ВОР, нет в СО; Источник: 03-01/07.21П-ИОС 3.1 ГЧ. Спецификация л. 2 (Файл: 03-01_07.21П-ИОС3.1.pdf, стр.: 1) | E99: ссылка на документ перенесена из «Тип, марка» в примечание
A100: 431 | B100: C — Тип, марка | C100: 03-01/07.21П-ИОС 3.1 ГЧ. Спецификация л. 2 (Файл: 03-01_07.21П-ИОС3.1.pdf, стр.: 1) | E100: ссылка на документ убрана из «Тип, марка»
...
